{"owner_type":"orgs","package_type":"container","owner_id":69635467,"owner":"shipwright-io","repo":"build","package":"base-git","date":"2024-11-21","size":"-1","versions":"1","tagged":"0","downloads":"41.4k","downloads_month":"57","downloads_week":"57","downloads_day":"0","raw_size":-1,"raw_versions":1,"raw_tagged":0,"raw_downloads":41434,"raw_downloads_month":57,"raw_downloads_week":57,"raw_downloads_day":0,"version":[{"id":308016180,"name":"sha256:a552a9355d041f9fb488854b8020729fef0206ba269e0705e282a1efeb77c1ff","date":"2024-11-21","newest":true,"latest":false,"size":"-1","downloads":"57","downloads_month":"57","downloads_week":"57","downloads_day":"0","raw_size":-1,"raw_downloads":57,"raw_downloads_month":57,"raw_downloads_week":57,"raw_downloads_day":0,"tags":[]}]}
