{"owner_type":"users","package_type":"container","owner_id":6949966,"owner":"jonashackt","repo":"microservice-ui-nuxt-js","package":"microservice-ui-nuxt-js","date":"2024-11-13","size":"-1","versions":"2","tagged":"2","downloads":"4.3k","downloads_month":"6","downloads_week":"0","downloads_day":"0","raw_size":-1,"raw_versions":2,"raw_tagged":2,"raw_downloads":4344,"raw_downloads_month":6,"raw_downloads_week":0,"raw_downloads_day":0,"version":[{"id":294077054,"name":"sha256:ea6ca71357b45fd734f1da547b77efe1342f8ab89318f0df3142be53aa385a67","date":"2024-11-13","newest":false,"latest":false,"size":"167.5 MB","downloads":"3","downloads_month":"3","downloads_week":"0","downloads_day":"0","raw_size":167545958,"raw_downloads":3,"raw_downloads_month":3,"raw_downloads_week":0,"raw_downloads_day":0,"tags":["22.04"]},{"id":298577546,"name":"sha256:5eb02cb78e706ca2be2c301646d34cb1c52ab088074c252d845c0bc4639c5e98","date":"2024-11-13","newest":true,"latest":true,"size":"167.5 MB","downloads":"3","downloads_month":"3","downloads_week":"0","downloads_day":"0","raw_size":167543437,"raw_downloads":3,"raw_downloads_month":3,"raw_downloads_week":0,"raw_downloads_day":0,"tags":["22.04"]}]}
