{"owner_type":"users","package_type":"container","owner_id":1172179,"owner":"v0l","repo":"deb-mirror-net","package":"deb-mirror-net","date":"2024-12-05","size":"-1","versions":"6","tagged":"1","downloads":"1.3k","downloads_month":"11","downloads_week":"0","downloads_day":"0","raw_size":-1,"raw_versions":6,"raw_tagged":1,"raw_downloads":1362,"raw_downloads_month":11,"raw_downloads_week":0,"raw_downloads_day":0,"version":[{"id":542904,"name":"sha256:3107977fa2e1600c23e1e190c6fa8ba894797e472e10dcce69c634f0560cffa8","date":"2024-12-05","newest":false,"latest":false,"size":"77.3 MB","downloads":"0","downloads_month":"0","downloads_week":"0","downloads_day":"0","raw_size":77365998,"raw_downloads":0,"raw_downloads_month":0,"raw_downloads_week":0,"raw_downloads_day":0,"tags":[]},{"id":542911,"name":"sha256:df6ce8645c09443333c374b95f2ae8182728020cf39392adeac032db39595e07","date":"2024-12-05","newest":false,"latest":false,"size":"77.3 MB","downloads":"0","downloads_month":"0","downloads_week":"0","downloads_day":"0","raw_size":77366009,"raw_downloads":0,"raw_downloads_month":0,"raw_downloads_week":0,"raw_downloads_day":0,"tags":[]},{"id":542996,"name":"sha256:32514562d67e1c409ce1ad32ca85913a680e2d73115729afc6ffa0c5d459edc6","date":"2024-12-05","newest":false,"latest":false,"size":"77.3 MB","downloads":"6","downloads_month":"0","downloads_week":"0","downloads_day":"0","raw_size":77365995,"raw_downloads":6,"raw_downloads_month":0,"raw_downloads_week":0,"raw_downloads_day":0,"tags":[]},{"id":544505,"name":"sha256:2529911c8b37340ef92027d8966576ea9b4a269de6d68b1fdf39066e47ec2991","date":"2024-12-05","newest":false,"latest":false,"size":"77.3 MB","downloads":"0","downloads_month":"0","downloads_week":"0","downloads_day":"0","raw_size":77365995,"raw_downloads":0,"raw_downloads_month":0,"raw_downloads_week":0,"raw_downloads_day":0,"tags":[]},{"id":544515,"name":"sha256:e0c8d54f36738948378a32f9a80690d1999938557db2863d5d8b21a8fc22b0db","date":"2024-12-05","newest":false,"latest":false,"size":"77.3 MB","downloads":"2","downloads_month":"1","downloads_week":"0","downloads_day":"0","raw_size":77365998,"raw_downloads":2,"raw_downloads_month":1,"raw_downloads_week":0,"raw_downloads_day":0,"tags":[]},{"id":712267,"name":"sha256:bab721d9bd73c505f4dde136434542404be1f9d2d982174890195452e0dc93b9","date":"2024-12-05","newest":true,"latest":true,"size":"-1","downloads":"585","downloads_month":"10","downloads_week":"0","downloads_day":"0","raw_size":-1,"raw_downloads":585,"raw_downloads_month":10,"raw_downloads_week":0,"raw_downloads_day":0,"tags":["latest"]}]}
