<?xml version="1.0" encoding="UTF-8"?><bkg><owner_type>orgs</owner_type><package_type>container</package_type><owner_id>365230</owner_id><owner>DataDog</owner><repo>lading</repo><package>lading</package><date>2024-10-16</date><size>71 MB</size><versions>36</versions><tagged>6</tagged><downloads>10.7M</downloads><downloads_month>972</downloads_month><downloads_week>1.5k</downloads_week><downloads_day>1k</downloads_day><raw_size>71010253</raw_size><raw_versions>36</raw_versions><raw_tagged>6</raw_tagged><raw_downloads>10752290</raw_downloads><raw_downloads_month>972</raw_downloads_month><raw_downloads_week>1575</raw_downloads_week><raw_downloads_day>1035</raw_downloads_day><version><id>285089931</id><name>sha256:276e7802dad07ffd249b210d1003b810cbe0178800534b9adfccc1a88a2096b1</name><date>2024-10-16</date><newest>false</newest><latest>false</latest><size>10.7 kB</size><downloads>-1</downloads><downloads_month>-1</downloads_month><downloads_week>-1</downloads_week><downloads_day>-1</downloads_day><raw_size>10725</raw_size><raw_downloads>-1</raw_downloads><raw_downloads_month>-1</raw_downloads_month><raw_downloads_week>-1</raw_downloads_week><raw_downloads_day>-1</raw_downloads_day><tags></tags></version><version><id>285093190</id><name>sha256:767b5f8b68785e7a6ca78987491dd199594f112f082ae4a1e69796a201aa9f87</name><date>2024-10-16</date><newest>false</newest><latest>false</latest><size>10.7 kB</size><downloads>0</downloads><downloads_month>0</downloads_month><downloads_week>0</downloads_week><downloads_day>0</downloads_day><raw_size>10713</raw_size><raw_downloads>0</raw_downloads><raw_downloads_month>0</raw_downloads_month><raw_downloads_week>0</raw_downloads_week><raw_downloads_day>0</raw_downloads_day><tags></tags></version><version><id>285093191</id><name>sha256:0cfe674bae6a7cf9ef9b677635e613b8e710b271dda1aae9527643e2ddf0a773</name><date>2024-10-16</date><newest>false</newest><latest>false</latest><size>34.7 MB</size><downloads>0</downloads><downloads_month>0</downloads_month><downloads_week>0</downloads_week><downloads_day>0</downloads_day><raw_size>34792211</raw_size><raw_downloads>0</raw_downloads><raw_downloads_month>0</raw_downloads_month><raw_downloads_week>0</raw_downloads_week><raw_downloads_day>0</raw_downloads_day><tags></tags></version><version><id>285093193</id><name>sha256:ae2a2bf57dced3a64a74cb4f11e512cceaa4bde08571c04e27f82158babbe382</name><date>2024-10-16</date><newest>false</newest><latest>false</latest><size>10.7 kB</size><downloads>0</downloads><downloads_month>0</downloads_month><downloads_week>0</downloads_week><downloads_day>0</downloads_day><raw_size>10713</raw_size><raw_downloads>0</raw_downloads><raw_downloads_month>0</raw_downloads_month><raw_downloads_week>0</raw_downloads_week><raw_downloads_day>0</raw_downloads_day><tags></tags></version><version><id>285373804</id><name>sha256:5254417822b6df6ec87dae4fb5d3abcbc63e815d6357e633e05bd6c2089078c2</name><date>2024-10-16</date><newest>false</newest><latest>false</latest><size>10.7 kB</size><downloads>0</downloads><downloads_month>0</downloads_month><downloads_week>0</downloads_week><downloads_day>0</downloads_day><raw_size>10713</raw_size><raw_downloads>0</raw_downloads><raw_downloads_month>0</raw_downloads_month><raw_downloads_week>0</raw_downloads_week><raw_downloads_day>0</raw_downloads_day><tags></tags></version><version><id>285373808</id><name>sha256:18403caddc955a79960d8b0acbe33f02c4832f3db59e9f6edb554f7011935b3c</name><date>2024-10-16</date><newest>false</newest><latest>false</latest><size>34.7 MB</size><downloads>0</downloads><downloads_month>0</downloads_month><downloads_week>0</downloads_week><downloads_day>0</downloads_day><raw_size>34792211</raw_size><raw_downloads>0</raw_downloads><raw_downloads_month>0</raw_downloads_month><raw_downloads_week>0</raw_downloads_week><raw_downloads_day>0</raw_downloads_day><tags></tags></version><version><id>285373815</id><name>sha256:8caeb343c718f2d95fad516c04743ca1f2ce63a32d43e70c27b4246a9c347783</name><date>2024-10-16</date><newest>false</newest><latest>false</latest><size>10.7 kB</size><downloads>2</downloads><downloads_month>2</downloads_month><downloads_week>2</downloads_week><downloads_day>0</downloads_day><raw_size>10713</raw_size><raw_downloads>2</raw_downloads><raw_downloads_month>2</raw_downloads_month><raw_downloads_week>2</raw_downloads_week><raw_downloads_day>0</raw_downloads_day><tags></tags></version><version><id>285373818</id><name>sha256:2d08c56d3f5b46749fa3694b7c5abc9287559a8e1b264ca147eb01c90d18a6ae</name><date>2024-10-16</date><newest>false</newest><latest>false</latest><size>71 MB</size><downloads>0</downloads><downloads_month>0</downloads_month><downloads_week>0</downloads_week><downloads_day>0</downloads_day><raw_size>71010610</raw_size><raw_downloads>0</raw_downloads><raw_downloads_month>0</raw_downloads_month><raw_downloads_week>0</raw_downloads_week><raw_downloads_day>0</raw_downloads_day><tags>sha-ac668277ffd553b1113576175b79356c9bafb46f</tags></version><version><id>285374885</id><name>sha256:8832f6815daf1e4bef53156edc21dc4c9c861e09ac4ef9eab80b9a91d4a277a8</name><date>2024-10-16</date><newest>false</newest><latest>false</latest><size>34.7 MB</size><downloads>0</downloads><downloads_month>0</downloads_month><downloads_week>0</downloads_week><downloads_day>0</downloads_day><raw_size>34792001</raw_size><raw_downloads>0</raw_downloads><raw_downloads_month>0</raw_downloads_month><raw_downloads_week>0</raw_downloads_week><raw_downloads_day>0</raw_downloads_day><tags></tags></version><version><id>285374887</id><name>sha256:6347d339d4b15054abb486fe9ee1a0b008427675aa181655101ff9adda6577de</name><date>2024-10-16</date><newest>false</newest><latest>false</latest><size>36.2 MB</size><downloads>0</downloads><downloads_month>0</downloads_month><downloads_week>0</downloads_week><downloads_day>0</downloads_day><raw_size>36200929</raw_size><raw_downloads>0</raw_downloads><raw_downloads_month>0</raw_downloads_month><raw_downloads_week>0</raw_downloads_week><raw_downloads_day>0</raw_downloads_day><tags></tags></version><version><id>285374890</id><name>sha256:df01e430ab163cbd9cc0ce55270395c946ea614939b786f9461023952b053274</name><date>2024-10-16</date><newest>false</newest><latest>false</latest><size>71 MB</size><downloads>-1</downloads><downloads_month>-1</downloads_month><downloads_week>-1</downloads_week><downloads_day>-1</downloads_day><raw_size>71010930</raw_size><raw_downloads>-1</raw_downloads><raw_downloads_month>-1</raw_downloads_month><raw_downloads_week>-1</raw_downloads_week><raw_downloads_day>-1</raw_downloads_day><tags>sha-be55ea8cc9a5bccff3dd8cdd269d82222acc3c55</tags></version><version><id>285513881</id><name>sha256:824e416109bda33ef4f49f532e0e4d46539947e1102445d1b398bb6bab55bd68</name><date>2024-10-16</date><newest>false</newest><latest>false</latest><size>36.2 MB</size><downloads>4</downloads><downloads_month>4</downloads_month><downloads_week>4</downloads_week><downloads_day>0</downloads_day><raw_size>36201781</raw_size><raw_downloads>4</raw_downloads><raw_downloads_month>4</raw_downloads_month><raw_downloads_week>4</raw_downloads_week><raw_downloads_day>0</raw_downloads_day><tags></tags></version><version><id>285513887</id><name>sha256:854ae1ac54c7ba5d8e63a3f91bc99a9e55cb3bc06fb076224d8b6ce69762eaea</name><date>2024-10-16</date><newest>false</newest><latest>false</latest><size>34.7 MB</size><downloads>4</downloads><downloads_month>4</downloads_month><downloads_week>4</downloads_week><downloads_day>1</downloads_day><raw_size>34792714</raw_size><raw_downloads>4</raw_downloads><raw_downloads_month>4</raw_downloads_month><raw_downloads_week>4</raw_downloads_week><raw_downloads_day>1</raw_downloads_day><tags></tags></version><version><id>285513889</id><name>sha256:65a8764b4e70b1bc7dc0a6c785fb99210f2e0dcc6e16bc00e12c8c1806c32477</name><date>2024-10-16</date><newest>false</newest><latest>false</latest><size>10.8 kB</size><downloads>0</downloads><downloads_month>0</downloads_month><downloads_week>0</downloads_week><downloads_day>0</downloads_day><raw_size>10892</raw_size><raw_downloads>0</raw_downloads><raw_downloads_month>0</raw_downloads_month><raw_downloads_week>0</raw_downloads_week><raw_downloads_day>0</raw_downloads_day><tags></tags></version><version><id>285519131</id><name>sha256:460ad887cabe984ef54fd543c420f1fe2ae0cf383eb145dc4ec66f22d63e95aa</name><date>2024-10-16</date><newest>false</newest><latest>false</latest><size>10.7 kB</size><downloads>-1</downloads><downloads_month>-1</downloads_month><downloads_week>-1</downloads_week><downloads_day>-1</downloads_day><raw_size>10725</raw_size><raw_downloads>-1</raw_downloads><raw_downloads_month>-1</raw_downloads_month><raw_downloads_week>-1</raw_downloads_week><raw_downloads_day>-1</raw_downloads_day><tags></tags></version><version><id>285519135</id><name>sha256:9b1c024b6c9b71fd06b3016958a38824fcac364158a23c9fa3ec4b90c0617858</name><date>2024-10-16</date><newest>false</newest><latest>false</latest><size>34.7 MB</size><downloads>-1</downloads><downloads_month>-1</downloads_month><downloads_week>-1</downloads_week><downloads_day>-1</downloads_day><raw_size>34790996</raw_size><raw_downloads>-1</raw_downloads><raw_downloads_month>-1</raw_downloads_month><raw_downloads_week>-1</raw_downloads_week><raw_downloads_day>-1</raw_downloads_day><tags></tags></version><version><id>285519136</id><name>sha256:c38db024487a4881e4aea89a4738e8fd5ce583253f8b78eafb94f0b4cd0ba7bc</name><date>2024-10-16</date><newest>false</newest><latest>false</latest><size>10.8 kB</size><downloads>3</downloads><downloads_month>3</downloads_month><downloads_week>3</downloads_week><downloads_day>0</downloads_day><raw_size>10892</raw_size><raw_downloads>3</raw_downloads><raw_downloads_month>3</raw_downloads_month><raw_downloads_week>3</raw_downloads_week><raw_downloads_day>0</raw_downloads_day><tags></tags></version><version><id>285540836</id><name>sha256:968f2fde0479673b8371bb2c1645ab59b705586e6835ff6d7b868c4e92e19c53</name><date>2024-10-16</date><newest>false</newest><latest>false</latest><size>10.8 kB</size><downloads>3</downloads><downloads_month>3</downloads_month><downloads_week>3</downloads_week><downloads_day>0</downloads_day><raw_size>10892</raw_size><raw_downloads>3</raw_downloads><raw_downloads_month>3</raw_downloads_month><raw_downloads_week>3</raw_downloads_week><raw_downloads_day>0</raw_downloads_day><tags></tags></version><version><id>285540838</id><name>sha256:94fc27a6431c43b4fc2237edce8960ac0ddcd26200b7da3f0d5cd967a568d7df</name><date>2024-10-16</date><newest>false</newest><latest>false</latest><size>71 MB</size><downloads>-1</downloads><downloads_month>-1</downloads_month><downloads_week>-1</downloads_week><downloads_day>-1</downloads_day><raw_size>71010251</raw_size><raw_downloads>-1</raw_downloads><raw_downloads_month>-1</raw_downloads_month><raw_downloads_week>-1</raw_downloads_week><raw_downloads_day>-1</raw_downloads_day><tags></tags></version><version><id>285560485</id><name>sha256:ed528cfa85fb5d3652970a74eeaccd9b4049d41131343e383fda38290e7ff54b</name><date>2024-10-16</date><newest>false</newest><latest>false</latest><size>11.3 kB</size><downloads>-1</downloads><downloads_month>-1</downloads_month><downloads_week>-1</downloads_week><downloads_day>-1</downloads_day><raw_size>11329</raw_size><raw_downloads>-1</raw_downloads><raw_downloads_month>-1</raw_downloads_month><raw_downloads_week>-1</raw_downloads_week><raw_downloads_day>-1</raw_downloads_day><tags></tags></version><version><id>285560491</id><name>sha256:479a38d14ec93ec9a86c888da2dcc14e4f2de53a0b0a972be51e78278a18b343</name><date>2024-10-16</date><newest>false</newest><latest>false</latest><size>36.1 MB</size><downloads>854</downloads><downloads_month>854</downloads_month><downloads_week>679</downloads_week><downloads_day>498</downloads_day><raw_size>36199676</raw_size><raw_downloads>854</raw_downloads><raw_downloads_month>854</raw_downloads_month><raw_downloads_week>679</raw_downloads_week><raw_downloads_day>498</raw_downloads_day><tags></tags></version><version><id>285560492</id><name>sha256:cf375e60cd492cb595511cdfdc01f72de29116ef23bc30311a2e9e97a3bb229e</name><date>2024-10-16</date><newest>false</newest><latest>false</latest><size>11.4 kB</size><downloads>4</downloads><downloads_month>4</downloads_month><downloads_week>4</downloads_week><downloads_day>0</downloads_day><raw_size>11496</raw_size><raw_downloads>4</raw_downloads><raw_downloads_month>4</raw_downloads_month><raw_downloads_week>4</raw_downloads_week><raw_downloads_day>0</raw_downloads_day><tags></tags></version><version><id>285560494</id><name>sha256:6e41f777e358e5c99aac5323c1fdac83376648a1f3992bb8e656f20e4f022fe7</name><date>2024-10-16</date><newest>false</newest><latest>false</latest><size>71 MB</size><downloads>94</downloads><downloads_month>94</downloads_month><downloads_week>872</downloads_week><downloads_day>541</downloads_day><raw_size>71011392</raw_size><raw_downloads>94</raw_downloads><raw_downloads_month>94</raw_downloads_month><raw_downloads_week>872</raw_downloads_week><raw_downloads_day>541</raw_downloads_day><tags>0.23.3</tags><tags>sha-1d599e06a0e0da4cbbabc267f02b526aadea3091</tags><tags>0.23</tags><tags>latest</tags><tags>0</tags></version><version><id>285582467</id><name>sha256:cd7e0a34029fb6c10a11bf5874305f29ce8221e6433b3539e6c5f1ec323a958f</name><date>2024-10-16</date><newest>false</newest><latest>false</latest><size>34.7 MB</size><downloads>0</downloads><downloads_month>0</downloads_month><downloads_week>0</downloads_week><downloads_day>0</downloads_day><raw_size>34792500</raw_size><raw_downloads>0</raw_downloads><raw_downloads_month>0</raw_downloads_month><raw_downloads_week>0</raw_downloads_week><raw_downloads_day>0</raw_downloads_day><tags></tags></version><version><id>285582477</id><name>sha256:06ea4fb569567faf286f35efa4d9ad032b2ad7804a889654f8fa495f5aba017d</name><date>2024-10-16</date><newest>false</newest><latest>false</latest><size>10.8 kB</size><downloads>3</downloads><downloads_month>3</downloads_month><downloads_week>3</downloads_week><downloads_day>0</downloads_day><raw_size>10892</raw_size><raw_downloads>3</raw_downloads><raw_downloads_month>3</raw_downloads_month><raw_downloads_week>3</raw_downloads_week><raw_downloads_day>0</raw_downloads_day><tags></tags></version><version><id>285582480</id><name>sha256:85313d4c4b6a1d114f2be8f22e7996cfa2e32b1e128b68207781a55c91e9cbea</name><date>2024-10-16</date><newest>false</newest><latest>false</latest><size>71 MB</size><downloads>-1</downloads><downloads_month>-1</downloads_month><downloads_week>-1</downloads_week><downloads_day>-1</downloads_day><raw_size>71010253</raw_size><raw_downloads>-1</raw_downloads><raw_downloads_month>-1</raw_downloads_month><raw_downloads_week>-1</raw_downloads_week><raw_downloads_day>-1</raw_downloads_day><tags>sha-3b8c71ac91adf02fedbb4ec3be337090406c474d</tags></version><version><id>286802612</id><name>sha256:e8484db5cbb2abdfe03f82b4d849e01353f3d3cdfe5540d92c0368cb8dc3f9bd</name><date>2024-10-16</date><newest>false</newest><latest>false</latest><size>36.1 MB</size><downloads>3</downloads><downloads_month>3</downloads_month><downloads_week>3</downloads_week><downloads_day>0</downloads_day><raw_size>36199753</raw_size><raw_downloads>3</raw_downloads><raw_downloads_month>3</raw_downloads_month><raw_downloads_week>3</raw_downloads_week><raw_downloads_day>0</raw_downloads_day><tags></tags></version><version><id>286802616</id><name>sha256:0cd37d26459053d0278aa019dd311bb94ef48e69794053468325357c81ab30b6</name><date>2024-10-16</date><newest>false</newest><latest>false</latest><size>10.5 kB</size><downloads>-1</downloads><downloads_month>-1</downloads_month><downloads_week>-1</downloads_week><downloads_day>-1</downloads_day><raw_size>10546</raw_size><raw_downloads>-1</raw_downloads><raw_downloads_month>-1</raw_downloads_month><raw_downloads_week>-1</raw_downloads_week><raw_downloads_day>-1</raw_downloads_day><tags></tags></version><version><id>286802622</id><name>sha256:985d59526acdc2b0a5729a6981556d47f95c410fe485b40c9c844a448632948a</name><date>2024-10-16</date><newest>false</newest><latest>false</latest><size>34.7 MB</size><downloads>-1</downloads><downloads_month>-1</downloads_month><downloads_week>-1</downloads_week><downloads_day>-1</downloads_day><raw_size>34790775</raw_size><raw_downloads>-1</raw_downloads><raw_downloads_month>-1</raw_downloads_month><raw_downloads_week>-1</raw_downloads_week><raw_downloads_day>-1</raw_downloads_day><tags></tags></version><version><id>286802625</id><name>sha256:f9034da284928614a02a22624e052b038e00b838471fd64f86fea166caa65f74</name><date>2024-10-16</date><newest>false</newest><latest>false</latest><size>10.7 kB</size><downloads>4</downloads><downloads_month>4</downloads_month><downloads_week>4</downloads_week><downloads_day>1</downloads_day><raw_size>10713</raw_size><raw_downloads>4</raw_downloads><raw_downloads_month>4</raw_downloads_month><raw_downloads_week>4</raw_downloads_week><raw_downloads_day>1</raw_downloads_day><tags></tags></version><version><id>288762359</id><name>sha256:8b98fd0e41d2bf5a0aa9df463dd293b2e24c31c3d14b98e51f77fdbb8769a176</name><date>2024-10-16</date><newest>false</newest><latest>false</latest><size>34.7 MB</size><downloads>0</downloads><downloads_month>0</downloads_month><downloads_week>0</downloads_week><downloads_day>0</downloads_day><raw_size>34792500</raw_size><raw_downloads>0</raw_downloads><raw_downloads_month>0</raw_downloads_month><raw_downloads_week>0</raw_downloads_week><raw_downloads_day>0</raw_downloads_day><tags></tags></version><version><id>288762364</id><name>sha256:7980363361830f838980fb2818f304e84e03d15702c6431e0e9ffaf4a43791e4</name><date>2024-10-16</date><newest>false</newest><latest>false</latest><size>10.7 kB</size><downloads>0</downloads><downloads_month>0</downloads_month><downloads_week>0</downloads_week><downloads_day>0</downloads_day><raw_size>10713</raw_size><raw_downloads>0</raw_downloads><raw_downloads_month>0</raw_downloads_month><raw_downloads_week>0</raw_downloads_week><raw_downloads_day>0</raw_downloads_day><tags></tags></version><version><id>288762368</id><name>sha256:4ca497e9c4454c2eb1aa5600fc95f197076f0e3fc9464ec44b44ffc7c7653d72</name><date>2024-10-16</date><newest>false</newest><latest>false</latest><size>71 MB</size><downloads>0</downloads><downloads_month>0</downloads_month><downloads_week>0</downloads_week><downloads_day>0</downloads_day><raw_size>71009895</raw_size><raw_downloads>0</raw_downloads><raw_downloads_month>0</raw_downloads_month><raw_downloads_week>0</raw_downloads_week><raw_downloads_day>0</raw_downloads_day><tags>sha-71ca5d2d0e6d51043c8e246fd901e8833c3d8b6c</tags></version><version><id>289718933</id><name>sha256:1156e8b5f73ccea13a578d47553ce4de8be0f6743cb02ec3427b086e717a8739</name><date>2024-10-16</date><newest>false</newest><latest>false</latest><size>10.8 kB</size><downloads>1</downloads><downloads_month>1</downloads_month><downloads_week>1</downloads_week><downloads_day>1</downloads_day><raw_size>10892</raw_size><raw_downloads>1</raw_downloads><raw_downloads_month>1</raw_downloads_month><raw_downloads_week>1</raw_downloads_week><raw_downloads_day>1</raw_downloads_day><tags></tags></version><version><id>289718944</id><name>sha256:13a7947f685efed034c68476f62683ccbf04291d195406b687e7ce68d43a9c79</name><date>2024-10-16</date><newest>false</newest><latest>false</latest><size>10.8 kB</size><downloads>1</downloads><downloads_month>1</downloads_month><downloads_week>1</downloads_week><downloads_day>1</downloads_day><raw_size>10892</raw_size><raw_downloads>1</raw_downloads><raw_downloads_month>1</raw_downloads_month><raw_downloads_week>1</raw_downloads_week><raw_downloads_day>1</raw_downloads_day><tags></tags></version><version><id>289718950</id><name>sha256:35bf80c0f9bc383fef74ba33ca0fcd7fc886c4cd63d57e37d9cbfa2a2c43f3db</name><date>2024-10-16</date><newest>true</newest><latest>true</latest><size>71 MB</size><downloads>-1</downloads><downloads_month>-1</downloads_month><downloads_week>-1</downloads_week><downloads_day>-1</downloads_day><raw_size>71010253</raw_size><raw_downloads>-1</raw_downloads><raw_downloads_month>-1</raw_downloads_month><raw_downloads_week>-1</raw_downloads_week><raw_downloads_day>-1</raw_downloads_day><tags>sha-df8c0003222848caffc0d6d4d6e957b6b04763f1</tags></version></bkg>
