{"owner_type":"orgs","package_type":"container","owner_id":2545424,"owner":"citusdata","repo":"citus","package":"citus-devcontainer","date":"2024-11-07","size":"-1","versions":"1","tagged":"1","downloads":"17.3k","downloads_month":"8","downloads_week":"0","downloads_day":"0","raw_size":-1,"raw_versions":1,"raw_tagged":1,"raw_downloads":17338,"raw_downloads_month":8,"raw_downloads_week":0,"raw_downloads_day":0,"version":[{"id":248649204,"name":"sha256:f9e005eaed031963eee616e69bd182137f3f7b9801c930cb51c9a1983c7b3211","date":"2024-11-07","newest":true,"latest":true,"size":"-1","downloads":"19","downloads_month":"8","downloads_week":"0","downloads_day":"0","raw_size":-1,"raw_downloads":19,"raw_downloads_month":8,"raw_downloads_week":0,"raw_downloads_day":0,"tags":["sha-76f60a7","pg17_kickoff"]}]}
