<?xml version="1.0" encoding="UTF-8"?><bkg><owner_type>users</owner_type><package_type>container</package_type><owner_id>405</owner_id><owner>timburks</owner><repo>registry-viewer</repo><package>registry-viewer</package><date>2024-09-30</date><size>15.3 MB</size><versions>62</versions><tagged>62</tagged><downloads>3.7k</downloads><downloads_month>1</downloads_month><downloads_week>0</downloads_week><downloads_day>0</downloads_day><raw_size>15353551</raw_size><raw_versions>62</raw_versions><raw_tagged>62</raw_tagged><raw_downloads>3754</raw_downloads><raw_downloads_month>1</raw_downloads_month><raw_downloads_week>0</raw_downloads_week><raw_downloads_day>0</raw_downloads_day><version><id>-1</id><name>latest</name><date>2024-09-30</date><newest>true</newest><latest>true</latest><size>15.3 MB</size><downloads>3.7k</downloads><downloads_month>1</downloads_month><downloads_week>0</downloads_week><downloads_day>0</downloads_day><raw_size>15353551</raw_size><raw_downloads>3754</raw_downloads><raw_downloads_month>1</raw_downloads_month><raw_downloads_week>0</raw_downloads_week><raw_downloads_day>0</raw_downloads_day><tags></tags></version><bkg>