{"owner_type":"orgs","package_type":"container","owner_id":36883688,"owner":"dclfbk","repo":"bikingimprover","package":"bikingimprover-setup","date":"2024-11-15","size":"591.1 MB","versions":"19","tagged":"19","downloads":"6.2k","downloads_month":"0","downloads_week":"0","downloads_day":"0","raw_size":591117908,"raw_versions":19,"raw_tagged":19,"raw_downloads":6200,"raw_downloads_month":0,"raw_downloads_week":0,"raw_downloads_day":0,"version":[{"id":102404874,"name":"sha256:ac3976cbc63df9a71630f2e511919e8a3330dcb4bffa8198a2d368b37e4941c7","date":"2024-11-15","newest":false,"latest":false,"size":"589.2 MB","downloads":"144","downloads_month":"0","downloads_week":"0","downloads_day":"0","raw_size":589268174,"raw_downloads":144,"raw_downloads_month":0,"raw_downloads_week":0,"raw_downloads_day":0,"tags":["c8d7ee086345672c3f87c1a40629caf866ec76bf"]},{"id":104382594,"name":"sha256:0699cdbf18bd606db88bb906341740303a137c4abcaa4d847a5752e6b1dab7ee","date":"2024-11-15","newest":false,"latest":false,"size":"589.6 MB","downloads":"144","downloads_month":"0","downloads_week":"0","downloads_day":"0","raw_size":589646860,"raw_downloads":144,"raw_downloads_month":0,"raw_downloads_week":0,"raw_downloads_day":0,"tags":["18f9929d419e2b1f665b5919703640b90fc45065"]},{"id":104752488,"name":"sha256:f133f597930ad0fdf7a1f6d502d3847549c16f6d8ab3b3ae0affd73b29180a07","date":"2024-11-15","newest":false,"latest":false,"size":"589.6 MB","downloads":"287","downloads_month":"0","downloads_week":"0","downloads_day":"0","raw_size":589650293,"raw_downloads":287,"raw_downloads_month":0,"raw_downloads_week":0,"raw_downloads_day":0,"tags":["089de21c93b9c2fc94e9ea88056432df1aabab91","docker_subbranch"]},{"id":105552243,"name":"sha256:e444b066b989c57823f0c666d62c467f085f78f35aaad20fa706c47dec65363b","date":"2024-11-15","newest":false,"latest":false,"size":"589.7 MB","downloads":"144","downloads_month":"0","downloads_week":"0","downloads_day":"0","raw_size":589772915,"raw_downloads":144,"raw_downloads_month":0,"raw_downloads_week":0,"raw_downloads_day":0,"tags":["e696476437c37e896e1da9070ea229f9610ed95d"]},{"id":105647181,"name":"sha256:17e74bf2ce9157cc7cff496608ac3c34a730b79a48adf1e6bfcfdfc431e499a7","date":"2024-11-15","newest":false,"latest":false,"size":"589.7 MB","downloads":"144","downloads_month":"0","downloads_week":"0","downloads_day":"0","raw_size":589774162,"raw_downloads":144,"raw_downloads_month":0,"raw_downloads_week":0,"raw_downloads_day":0,"tags":["37e42685ecfcb1ab1a3cdf7fc3ee493abe83ba2c"]},{"id":105991502,"name":"sha256:6cd9560d5af185a3d6aaf0c2009140653c4c54a78dd2e17b254e0c520107892e","date":"2024-11-15","newest":false,"latest":false,"size":"589.8 MB","downloads":"144","downloads_month":"0","downloads_week":"0","downloads_day":"0","raw_size":589800431,"raw_downloads":144,"raw_downloads_month":0,"raw_downloads_week":0,"raw_downloads_day":0,"tags":["b2b13d20f7ae6854708f1c58edf9006e42c13556"]},{"id":108050674,"name":"sha256:dad681346defec98f85aaa52618b2dcaf6706a4114ce1387b8d4b5af6e628980","date":"2024-11-15","newest":false,"latest":false,"size":"591.2 MB","downloads":"280","downloads_month":"2","downloads_week":"0","downloads_day":"0","raw_size":591248272,"raw_downloads":280,"raw_downloads_month":2,"raw_downloads_week":0,"raw_downloads_day":0,"tags":["0f9cfbc5301e927c9d00d01a6ad6907393f577e1","osm_import"]},{"id":108537553,"name":"sha256:05be8f2a2fd84a2fd6486fc85f0d28013b02b8adbe06d2d039346eb55009f2dc","date":"2024-11-15","newest":false,"latest":false,"size":"592.1 MB","downloads":"149","downloads_month":"0","downloads_week":"0","downloads_day":"0","raw_size":592187025,"raw_downloads":149,"raw_downloads_month":0,"raw_downloads_week":0,"raw_downloads_day":0,"tags":["d9591b5341abd750e11af227aa2984a0a7dd37d1"]},{"id":109556556,"name":"sha256:3dc7d194db7f089dcd5e6ad1346daa3b9814fd8526d04fb129f431409b2d7e38","date":"2024-11-15","newest":false,"latest":false,"size":"592.1 MB","downloads":"267","downloads_month":"0","downloads_week":"0","downloads_day":"0","raw_size":592197828,"raw_downloads":267,"raw_downloads_month":0,"raw_downloads_week":0,"raw_downloads_day":0,"tags":["4844ff5d84a2f0e51f2ec8c3a5efbc23378f1b77","docker"]},{"id":109563750,"name":"sha256:903ac4bfcd998edf352f245b8242ac9a505f128ecc0342118cc37a8a674737e5","date":"2024-11-15","newest":false,"latest":false,"size":"592.1 MB","downloads":"138","downloads_month":"1","downloads_week":"0","downloads_day":"0","raw_size":592198805,"raw_downloads":138,"raw_downloads_month":1,"raw_downloads_week":0,"raw_downloads_day":0,"tags":["3d124d7c75c9b6928ba1a11bb373a952ffe7b125"]},{"id":110538707,"name":"sha256:c20511e7e568f9c939995c1440fa751a7715fe123112a84fd1b132d74fe5a2d9","date":"2024-11-15","newest":false,"latest":false,"size":"590.4 MB","downloads":"132","downloads_month":"1","downloads_week":"0","downloads_day":"0","raw_size":590459993,"raw_downloads":132,"raw_downloads_month":1,"raw_downloads_week":0,"raw_downloads_day":0,"tags":["e1347084ed9f565a4b5ba7b75d9305f6e670009c"]},{"id":142194593,"name":"sha256:fdc0a1baf90b768ea6da0e64888132cae50b762a3345a54a52338e07cf0a6c74","date":"2024-11-15","newest":false,"latest":false,"size":"614.8 MB","downloads":"105","downloads_month":"0","downloads_week":"0","downloads_day":"0","raw_size":614874499,"raw_downloads":105,"raw_downloads_month":0,"raw_downloads_week":0,"raw_downloads_day":0,"tags":["439abdc18d3b779456cab521f7e4790193fafba8"]},{"id":143440876,"name":"sha256:6903c72b1195fc21bb25a16f754b79f88477c4469b75995eb747c110105c4c11","date":"2024-11-15","newest":true,"latest":false,"size":"615.3 MB","downloads":"104","downloads_month":"1","downloads_week":"0","downloads_day":"0","raw_size":615322604,"raw_downloads":104,"raw_downloads_month":1,"raw_downloads_week":0,"raw_downloads_day":0,"tags":["fab081f2b3ea27bacd9a34bd2d859e102e97330c"]},{"id":97307430,"name":"sha256:a962f5181c3836c718e221b84bc003f34c799412082751d970b86b2d15854d11","date":"2024-11-15","newest":false,"latest":false,"size":"588.6 MB","downloads":"0","downloads_month":"0","downloads_week":"0","downloads_day":"0","raw_size":588626234,"raw_downloads":0,"raw_downloads_month":0,"raw_downloads_week":0,"raw_downloads_day":0,"tags":["22.10"]},{"id":97328227,"name":"sha256:c329b95f9411a0781418bf31e3a6152ccd8bf2dc8079539e51b5f2cb673fc1e6","date":"2024-11-15","newest":false,"latest":false,"size":"588.6 MB","downloads":"145","downloads_month":"1","downloads_week":"0","downloads_day":"0","raw_size":588618619,"raw_downloads":145,"raw_downloads_month":1,"raw_downloads_week":0,"raw_downloads_day":0,"tags":["ce7b60764209780a87c2341615ecc3228a4ef1a3"]},{"id":97496944,"name":"sha256:c5b96182da876c3c3ca62286cf431081286f0bbfbaa572ea8819e1cf5b41a685","date":"2024-11-15","newest":false,"latest":false,"size":"588.6 MB","downloads":"145","downloads_month":"0","downloads_week":"0","downloads_day":"0","raw_size":588664490,"raw_downloads":145,"raw_downloads_month":0,"raw_downloads_week":0,"raw_downloads_day":0,"tags":["179da6119ee38d0b881969cf22f87a8b7183cb1f"]},{"id":97501803,"name":"sha256:75714b49aae58a476160d8537b3771968790ac43799b156c034f71c4ff7a5556","date":"2024-11-15","newest":false,"latest":false,"size":"588.6 MB","downloads":"145","downloads_month":"0","downloads_week":"0","downloads_day":"0","raw_size":588665358,"raw_downloads":145,"raw_downloads_month":0,"raw_downloads_week":0,"raw_downloads_day":0,"tags":["2e523c6b86714b54cec7fa3b40098073563ddd6e"]},{"id":97521095,"name":"sha256:4e2c4321fe9fbcf920d0af42fe08e7700b799789f6046e33341e094c1a95e4a0","date":"2024-11-15","newest":false,"latest":false,"size":"588.6 MB","downloads":"144","downloads_month":"0","downloads_week":"0","downloads_day":"0","raw_size":588664713,"raw_downloads":144,"raw_downloads_month":0,"raw_downloads_week":0,"raw_downloads_day":0,"tags":["3741c5739a2d2daa0bf19faf2132ceb8de4f3799"]},{"id":99285853,"name":"sha256:ad9d3e189115795204f2492b4253963d688e7ba1588543142f10b6aa165bacab","date":"2024-11-15","newest":false,"latest":true,"size":"591.1 MB","downloads":"154","downloads_month":"0","downloads_week":"0","downloads_day":"0","raw_size":591117908,"raw_downloads":154,"raw_downloads_month":0,"raw_downloads_week":0,"raw_downloads_day":0,"tags":["bb7af5581f3c42a27e0d86aa706ab8ee89ffa269"]}]}
