{"owner_type":"users","package_type":"container","owner_id":20770,"owner":"dottorblaster","repo":"barbecue","package":"barbecue-hana_node02","date":"2024-09-30","size":"54.3 MB","versions":"2","tagged":"2","downloads":"347","downloads_month":"8","downloads_week":"6","downloads_day":"0","raw_size":54370936,"raw_versions":2,"raw_tagged":2,"raw_downloads":347,"raw_downloads_month":8,"raw_downloads_week":6,"raw_downloads_day":0,"version":[{"id":124303111,"name":"sha256:4304a19a5e7f7588f0e00ff9f0c675e5328571062aee4d046d33bcab9f5e047f","date":"2024-09-30","newest":false,"latest":false,"size":"54.2 MB","downloads":"2","downloads_month":"2","downloads_week":"2","downloads_day":"0","raw_size":54267539,"raw_downloads":2,"raw_downloads_month":2,"raw_downloads_week":2,"raw_downloads_day":0,"tags":["nullnull[]"]},{"id":128536550,"name":"sha256:e14cbd526485a2dab0e2c4190be95fcdaf2b8696dba04d35ca5d775350273170","date":"2024-09-30","newest":true,"latest":true,"size":"54.3 MB","downloads":"115","downloads_month":"6","downloads_week":"4","downloads_day":"0","raw_size":54370936,"raw_downloads":115,"raw_downloads_month":6,"raw_downloads_week":4,"raw_downloads_day":0,"tags":["latest"]}]}
