{"owner_type":"users","package_type":"container","owner_id":3308,"owner":"ddollar","repo":"images","package":"go","date":"2024-08-26","size":"997.4 MB","versions":"16","tagged":"16","downloads":"5k","downloads_month":"203","downloads_week":"160","downloads_day":"16","raw_size":997400344,"raw_versions":16,"raw_tagged":16,"raw_downloads":5011,"raw_downloads_month":203,"raw_downloads_week":160,"raw_downloads_day":16,"version":[{"id":100538345,"name":"sha256:4957495e3460ee0c7f35a749ab8eae45a979d4589b70e367abd7ab22df051a85","date":"2024-08-26","newest":false,"latest":false,"size":"452.4 MB","downloads":"20","downloads_month":"12","downloads_week":"10","downloads_day":"1","raw_size":452431028,"raw_downloads":20,"raw_downloads_month":12,"raw_downloads_week":10,"raw_downloads_day":1,"tags":["nullnull[]"]},{"id":100538346,"name":"sha256:90058da230b60a188aaa211cd7a67b3a1c42899e78eb442ce30dc894334e2c0d","date":"2024-08-26","newest":false,"latest":false,"size":"442 MB","downloads":"14","downloads_month":"13","downloads_week":"9","downloads_day":"1","raw_size":442049152,"raw_downloads":14,"raw_downloads_month":13,"raw_downloads_week":9,"raw_downloads_day":1,"tags":["nullnull[]"]},{"id":100538364,"name":"sha256:35e44f2e351752a2e286cd11043f555aefbe5cfbee7d5f4e32503c6d9fae00fc","date":"2024-08-26","newest":false,"latest":false,"size":"452.5 MB","downloads":"12","downloads_month":"12","downloads_week":"10","downloads_day":"1","raw_size":452572482,"raw_downloads":12,"raw_downloads_month":12,"raw_downloads_week":10,"raw_downloads_day":1,"tags":["nullnull[]"]},{"id":100538365,"name":"sha256:6dc993350cafb3959cae8d6519751979647d1c3115439ec7364c1351b1098606","date":"2024-08-26","newest":false,"latest":false,"size":"22.8 kB","downloads":"12","downloads_month":"12","downloads_week":"10","downloads_day":"1","raw_size":22841,"raw_downloads":12,"raw_downloads_month":12,"raw_downloads_week":10,"raw_downloads_day":1,"tags":["nullnull[]"]},{"id":100538367,"name":"sha256:91a4ab7ea691cab84385570bb461f9ffd604bb76f2020eaa47321e18621e45e9","date":"2024-08-26","newest":false,"latest":false,"size":"442.2 MB","downloads":"11","downloads_month":"11","downloads_week":"10","downloads_day":"1","raw_size":442211290,"raw_downloads":11,"raw_downloads_month":11,"raw_downloads_week":10,"raw_downloads_day":1,"tags":["nullnull[]"]},{"id":100538368,"name":"sha256:6554926611fd3216c04eee78a8812ec0ec9073ad92850a1a114dd08442002b9d","date":"2024-08-26","newest":false,"latest":false,"size":"22.8 kB","downloads":"12","downloads_month":"12","downloads_week":"10","downloads_day":"1","raw_size":22833,"raw_downloads":12,"raw_downloads_month":12,"raw_downloads_week":10,"raw_downloads_day":1,"tags":["nullnull[]"]},{"id":100538371,"name":"sha256:ab56595a14df85a931d084878ddb74b5f8af8a850bbe45f599f4268de3ae2797","date":"2024-08-26","newest":false,"latest":false,"size":"452.3 MB","downloads":"13","downloads_month":"13","downloads_week":"10","downloads_day":"1","raw_size":452375465,"raw_downloads":13,"raw_downloads_month":13,"raw_downloads_week":10,"raw_downloads_day":1,"tags":["nullnull[]"]},{"id":100538373,"name":"sha256:766288aa5de9bae727db6c20045f9b6a79a61326519d1af3f4d61e52e27346f4","date":"2024-08-26","newest":false,"latest":false,"size":"441.9 MB","downloads":"12","downloads_month":"12","downloads_week":"10","downloads_day":"1","raw_size":441989602,"raw_downloads":12,"raw_downloads_month":12,"raw_downloads_week":10,"raw_downloads_day":1,"tags":["nullnull[]"]},{"id":100538374,"name":"sha256:13f5f51cdcc6c87b367b7b4dc6aea72961970c660c821be188005b919a952ee3","date":"2024-08-26","newest":false,"latest":false,"size":"21.5 kB","downloads":"12","downloads_month":"12","downloads_week":"10","downloads_day":"1","raw_size":21521,"raw_downloads":12,"raw_downloads_month":12,"raw_downloads_week":10,"raw_downloads_day":1,"tags":["nullnull[]"]},{"id":100538386,"name":"sha256:c757d5e58279f2655a26d63a64dfe4dd1d46bc8a6ee507970d05b35cc8110c3b","date":"2024-08-26","newest":false,"latest":false,"size":"21.5 kB","downloads":"12","downloads_month":"12","downloads_week":"10","downloads_day":"1","raw_size":21527,"raw_downloads":12,"raw_downloads_month":12,"raw_downloads_week":10,"raw_downloads_day":1,"tags":["nullnull[]"]},{"id":100538388,"name":"sha256:1cbebfe3fdab170c70cbf43feca5ddba42f1c3e694f4e786f88dbaab96f48fb8","date":"2024-08-26","newest":false,"latest":false,"size":"442 MB","downloads":"12","downloads_month":"12","downloads_week":"10","downloads_day":"1","raw_size":442049297,"raw_downloads":12,"raw_downloads_month":12,"raw_downloads_week":10,"raw_downloads_day":1,"tags":["nullnull[]"]},{"id":128010259,"name":"sha256:c933226917569a1071895861de86050e65d8131f65d338635c8707920c4c751d","date":"2024-08-26","newest":false,"latest":false,"size":"16.6 kB","downloads":"12","downloads_month":"12","downloads_week":"10","downloads_day":"1","raw_size":16619,"raw_downloads":12,"raw_downloads_month":12,"raw_downloads_week":10,"raw_downloads_day":1,"tags":["nullnull[]"]},{"id":128010316,"name":"sha256:875abe65b85785548ebe4bca4cda1a74f959c7601a1c36211154fc6a2cb13af8","date":"2024-08-26","newest":false,"latest":false,"size":"907.7 MB","downloads":"64","downloads_month":"16","downloads_week":"10","downloads_day":"0","raw_size":907760019,"raw_downloads":64,"raw_downloads_month":16,"raw_downloads_week":10,"raw_downloads_day":0,"tags":["nullnull[]"]},{"id":199353088,"name":"sha256:67171e4787b114b7e4f2427d7d1d81b29bc83d2af66eabbe07eb7be20f4f46d6","date":"2024-08-26","newest":false,"latest":false,"size":"2.1 kB","downloads":"12","downloads_month":"12","downloads_week":"10","downloads_day":"1","raw_size":2162,"raw_downloads":12,"raw_downloads_month":12,"raw_downloads_week":10,"raw_downloads_day":1,"tags":["nullnull[]"]},{"id":199354089,"name":"sha256:8b2e581edab0b790ee3d38e04dcbe8ddeac7ec59c51e7bd6f35c454a491cd981","date":"2024-08-26","newest":false,"latest":false,"size":"493.8 MB","downloads":"12","downloads_month":"12","downloads_week":"9","downloads_day":"1","raw_size":493843031,"raw_downloads":12,"raw_downloads_month":12,"raw_downloads_week":9,"raw_downloads_day":1,"tags":["nullnull[]"]},{"id":199354118,"name":"sha256:38bf5b01cbfd048af6d5f94f75d043ac94ce9c8ea00bf50479b775a18036ca1e","date":"2024-08-26","newest":true,"latest":true,"size":"997.4 MB","downloads":"44","downloads_month":"18","downloads_week":"12","downloads_day":"2","raw_size":997400344,"raw_downloads":44,"raw_downloads_month":18,"raw_downloads_week":12,"raw_downloads_day":2,"tags":["1.22"]}]}
