{"owner_type":"users","package_type":"container","owner_id":14123216,"owner":"loafoe","repo":"lessor","package":"lessor","date":"2024-11-06","size":"17.5 MB","versions":"10","tagged":"0","downloads":"3.5k","downloads_month":"50","downloads_week":"0","downloads_day":"0","raw_size":17563551,"raw_versions":10,"raw_tagged":0,"raw_downloads":3511,"raw_downloads_month":50,"raw_downloads_week":0,"raw_downloads_day":0,"version":[{"id":128695337,"name":"sha256:0877aea6255e0800c03dc30636646525c63802ef4358e3c25d561d1e375599bc","date":"2024-11-06","newest":false,"latest":false,"size":"18.1 MB","downloads":"6","downloads_month":"5","downloads_week":"0","downloads_day":"0","raw_size":18136122,"raw_downloads":6,"raw_downloads_month":5,"raw_downloads_week":0,"raw_downloads_day":0,"tags":[]},{"id":128695339,"name":"sha256:6dece9d81880208f9a4c28d72f0f90bd80c40fdb4ab2a9ee9514e974439a7d58","date":"2024-11-06","newest":false,"latest":false,"size":"2.1 kB","downloads":"6","downloads_month":"5","downloads_week":"0","downloads_day":"0","raw_size":2169,"raw_downloads":6,"raw_downloads_month":5,"raw_downloads_week":0,"raw_downloads_day":0,"tags":[]},{"id":128695340,"name":"sha256:13bcf46d55a073a6179d391cff48be95dee8860ca607a69bf6344eefc6a8c711","date":"2024-11-06","newest":false,"latest":false,"size":"-1","downloads":"12","downloads_month":"10","downloads_week":"0","downloads_day":"0","raw_size":-1,"raw_downloads":12,"raw_downloads_month":10,"raw_downloads_week":0,"raw_downloads_day":0,"tags":[]},{"id":135786836,"name":"sha256:7fec8704c15c133f21375870747b4a200f08e10ca2d7dca5ee7a56df7c3e1467","date":"2024-11-06","newest":false,"latest":false,"size":"18.1 MB","downloads":"6","downloads_month":"5","downloads_week":"0","downloads_day":"0","raw_size":18137545,"raw_downloads":6,"raw_downloads_month":5,"raw_downloads_week":0,"raw_downloads_day":0,"tags":[]},{"id":143066412,"name":"sha256:63b7b0d9f4bba3885bb94d0fb9499e040553dd1dd41df76a53af68f76502ba0d","date":"2024-11-06","newest":false,"latest":false,"size":"2.1 kB","downloads":"6","downloads_month":"6","downloads_week":"0","downloads_day":"0","raw_size":2169,"raw_downloads":6,"raw_downloads_month":6,"raw_downloads_week":0,"raw_downloads_day":0,"tags":[]},{"id":145805348,"name":"sha256:21a9d305941f1fa15dda8516316d4fab3cc0008db6e7923db706627129ae9087","date":"2024-11-06","newest":false,"latest":false,"size":"-1","downloads":"12","downloads_month":"10","downloads_week":"0","downloads_day":"0","raw_size":-1,"raw_downloads":12,"raw_downloads_month":10,"raw_downloads_week":0,"raw_downloads_day":0,"tags":[]},{"id":168914657,"name":"sha256:a56cfd9ce35fb4686129db27c70d8966f195701a4bf3d610cbdaac43f092c889","date":"2024-11-06","newest":false,"latest":false,"size":"-1","downloads":"12","downloads_month":"10","downloads_week":"0","downloads_day":"0","raw_size":-1,"raw_downloads":12,"raw_downloads_month":10,"raw_downloads_week":0,"raw_downloads_day":0,"tags":[]},{"id":168917144,"name":"sha256:8a006ad724e70d118817541982d641c5535f607e6dc5c68ba52d0d4d78c8f459","date":"2024-11-06","newest":false,"latest":false,"size":"2.1 kB","downloads":"7","downloads_month":"5","downloads_week":"0","downloads_day":"0","raw_size":2169,"raw_downloads":7,"raw_downloads_month":5,"raw_downloads_week":0,"raw_downloads_day":0,"tags":[]},{"id":182738066,"name":"sha256:8194de5c831eb03c499a5674b97577875c979ef09cca1b89d9c847df4920c074","date":"2024-11-06","newest":false,"latest":false,"size":"-1","downloads":"12","downloads_month":"10","downloads_week":"0","downloads_day":"0","raw_size":-1,"raw_downloads":12,"raw_downloads_month":10,"raw_downloads_week":0,"raw_downloads_day":0,"tags":[]},{"id":241614728,"name":"sha256:83c5e49fb4ff1dbd79c7a034e787d587484fc5a590c4b1aa5a7182bf896282ab","date":"2024-11-06","newest":true,"latest":false,"size":"17.5 MB","downloads":"9","downloads_month":"5","downloads_week":"0","downloads_day":"0","raw_size":17563551,"raw_downloads":9,"raw_downloads_month":5,"raw_downloads_week":0,"raw_downloads_day":0,"tags":[]}]}
