{"owner_type":"users","package_type":"container","owner_id":21136719,"owner":"ipitio","repo":"backage","package":"backage","date":"2024-10-19","size":"30.6 MB","versions":"1","tagged":"1","downloads":"29","downloads_month":"29","downloads_week":"29","downloads_day":"1","raw_size":30686910,"raw_versions":1,"raw_tagged":1,"raw_downloads":29,"raw_downloads_month":29,"raw_downloads_week":29,"raw_downloads_day":1,"version":[{"id":291501102,"name":"sha256:dc8a457521089bb87baf86d580941db063541824b2acdff5c605e2ad06ffdd05","date":"2024-10-19","newest":true,"latest":true,"size":"30.6 MB","downloads":"29","downloads_month":"29","downloads_week":"29","downloads_day":"1","raw_size":30686910,"raw_downloads":29,"raw_downloads_month":29,"raw_downloads_week":29,"raw_downloads_day":1,"tags":["master"]}]}
