{"owner_type":"users","package_type":"container","owner_id":47464438,"owner":"jbouhadoun","repo":"forked-adresse","package":"forked-adresse","date":"2024-11-04","size":"-1","versions":"8","tagged":"1","downloads":"134","downloads_month":"29","downloads_week":"1","downloads_day":"0","raw_size":-1,"raw_versions":8,"raw_tagged":1,"raw_downloads":134,"raw_downloads_month":29,"raw_downloads_week":1,"raw_downloads_day":0,"version":[{"id":272678396,"name":"sha256:b71d692ffed86c3d63e2dbd80a612e280bddb0c856d58dc738d8491933fd5e00","date":"2024-11-04","newest":false,"latest":false,"size":"434.6 MB","downloads":"6","downloads_month":"3","downloads_week":"0","downloads_day":"0","raw_size":434648529,"raw_downloads":6,"raw_downloads_month":3,"raw_downloads_week":0,"raw_downloads_day":0,"tags":[""]},{"id":272681086,"name":"sha256:7eba3cdd9c6879a653fd23bbc30b1165acbae480ce308876932895b3544966f8","date":"2024-11-04","newest":false,"latest":false,"size":"2 kB","downloads":"5","downloads_month":"2","downloads_week":"0","downloads_day":"0","raw_size":2086,"raw_downloads":5,"raw_downloads_month":2,"raw_downloads_week":0,"raw_downloads_day":0,"tags":[""]},{"id":274348100,"name":"sha256:038bd649e34d53d274ce0bcb50bcdbad1c89e972396ad7441027371c698b208d","date":"2024-11-04","newest":false,"latest":false,"size":"-1","downloads":"11","downloads_month":"6","downloads_week":"0","downloads_day":"0","raw_size":-1,"raw_downloads":11,"raw_downloads_month":6,"raw_downloads_week":0,"raw_downloads_day":0,"tags":[""]},{"id":274397213,"name":"sha256:39706ff1b2d4f083987b5fbeb7d210fe23005d263903007e9ff216190922ba0d","date":"2024-11-04","newest":false,"latest":false,"size":"2 kB","downloads":"5","downloads_month":"3","downloads_week":"0","downloads_day":"0","raw_size":2085,"raw_downloads":5,"raw_downloads_month":3,"raw_downloads_week":0,"raw_downloads_day":0,"tags":[""]},{"id":274397218,"name":"sha256:0f41cf536fca98b79333753e64533283f11914b888dd8f2f28c038ebd2e80e67","date":"2024-11-04","newest":false,"latest":false,"size":"-1","downloads":"12","downloads_month":"6","downloads_week":"0","downloads_day":"0","raw_size":-1,"raw_downloads":12,"raw_downloads_month":6,"raw_downloads_week":0,"raw_downloads_day":0,"tags":[""]},{"id":274847510,"name":"sha256:2d0b1516f47132fe1da1723ea774b2618e757456dc4fb82f4276866e7165e83b","date":"2024-11-04","newest":false,"latest":false,"size":"434.6 MB","downloads":"5","downloads_month":"3","downloads_week":"0","downloads_day":"0","raw_size":434648529,"raw_downloads":5,"raw_downloads_month":3,"raw_downloads_week":0,"raw_downloads_day":0,"tags":[""]},{"id":274847517,"name":"sha256:77bebb98fe25b3d0f47c4766ea99939a06aacb49a76200634adf6a7c0ee9d047","date":"2024-11-04","newest":false,"latest":false,"size":"2 kB","downloads":"5","downloads_month":"3","downloads_week":"0","downloads_day":"0","raw_size":2097,"raw_downloads":5,"raw_downloads_month":3,"raw_downloads_week":0,"raw_downloads_day":0,"tags":[""]},{"id":274848270,"name":"sha256:de8fa9df40480086c7f74564ce28edc2c6a7f6e1e09c1a3a6a8d1673ed43e72a","date":"2024-11-04","newest":true,"latest":true,"size":"-1","downloads":"11","downloads_month":"6","downloads_week":"1","downloads_day":"0","raw_size":-1,"raw_downloads":11,"raw_downloads_month":6,"raw_downloads_week":1,"raw_downloads_day":0,"tags":["main"]}]}
