{"owner_type":"orgs","package_type":"container","owner_id":90630635,"owner":"getAlby","repo":"nostr-wallet-connect-next","package":"nostr-wallet-connect-next","date":"2024-10-23","size":"104.8 MB","versions":"4","tagged":"0","downloads":"28.9k","downloads_month":"24","downloads_week":"8","downloads_day":"0","raw_size":104847169,"raw_versions":4,"raw_tagged":0,"raw_downloads":28912,"raw_downloads_month":24,"raw_downloads_week":8,"raw_downloads_day":0,"version":[{"id":239474461,"name":"sha256:f53c8c4edbc75dacf3e27e1a0b847b4b96cb13170f927c5c779f4c39dd75f8de","date":"2024-10-23","newest":false,"latest":false,"size":"103 MB","downloads":"6","downloads_month":"6","downloads_week":"2","downloads_day":"0","raw_size":103019305,"raw_downloads":6,"raw_downloads_month":6,"raw_downloads_week":2,"raw_downloads_day":0,"tags":[""]},{"id":239657728,"name":"sha256:3c2d291e0b85c8d2c905651a22beeb2f7c0bc85f5dd731b134f78676a92d922a","date":"2024-10-23","newest":false,"latest":false,"size":"103 MB","downloads":"6","downloads_month":"6","downloads_week":"2","downloads_day":"0","raw_size":103041573,"raw_downloads":6,"raw_downloads_month":6,"raw_downloads_week":2,"raw_downloads_day":0,"tags":[""]},{"id":239657730,"name":"sha256:323328d0e7b40e71d761f41d3587b7207d7686662bf823acbf0cb69fc502ead0","date":"2024-10-23","newest":false,"latest":false,"size":"2.4 kB","downloads":"6","downloads_month":"6","downloads_week":"2","downloads_day":"0","raw_size":2420,"raw_downloads":6,"raw_downloads_month":6,"raw_downloads_week":2,"raw_downloads_day":0,"tags":[""]},{"id":240593266,"name":"sha256:0066284cf8e5084209f6cf69af4b0871d15ddbd3988cb3c813e73705cd28b2bf","date":"2024-10-23","newest":true,"latest":false,"size":"104.8 MB","downloads":"6","downloads_month":"6","downloads_week":"2","downloads_day":"0","raw_size":104847169,"raw_downloads":6,"raw_downloads_month":6,"raw_downloads_week":2,"raw_downloads_day":0,"tags":[""]}]}
