<?xml version="1.0" encoding="UTF-8"?><bkg><owner_type>orgs</owner_type><package_type>container</package_type><owner_id>18304793</owner_id><owner>alan-turing-institute</owner><repo>reginald</repo><package>reginald_slackbot</package><date>2024-10-25</date><size>2.1 GB</size><versions>14</versions><tagged>14</tagged><downloads>677</downloads><downloads_month>14</downloads_month><downloads_week>0</downloads_week><downloads_day>0</downloads_day><raw_size>2147483647</raw_size><raw_versions>14</raw_versions><raw_tagged>14</raw_tagged><raw_downloads>677</raw_downloads><raw_downloads_month>14</raw_downloads_month><raw_downloads_week>0</raw_downloads_week><raw_downloads_day>0</raw_downloads_day><version><id>164716671</id><name>sha256:d2df3bafbb0925ffe113eefc46e7a589e4b29f07714050878d15b5b8603f0423</name><date>2024-10-25</date><newest>false</newest><latest>false</latest><size>2.1 GB</size><downloads>95</downloads><downloads_month>1</downloads_month><downloads_week>0</downloads_week><downloads_day>0</downloads_day><raw_size>2147483647</raw_size><raw_downloads>95</raw_downloads><raw_downloads_month>1</raw_downloads_month><raw_downloads_week>0</raw_downloads_week><raw_downloads_day>0</raw_downloads_day><tags>pulumi</tags></version><version><id>236069358</id><name>sha256:901d24652729943ed72698db1c10631495708786fa141a6137869fcbc6df558e</name><date>2024-10-25</date><newest>true</newest><latest>true</latest><size>2.1 GB</size><downloads>10</downloads><downloads_month>2</downloads_month><downloads_week>0</downloads_week><downloads_day>0</downloads_day><raw_size>2147483647</raw_size><raw_downloads>10</raw_downloads><raw_downloads_month>2</raw_downloads_month><raw_downloads_week>0</raw_downloads_week><raw_downloads_day>0</raw_downloads_day><tags>main</tags></version></bkg>
