<?xml version="1.0" encoding="UTF-8"?><bkg><owner_type>users</owner_type><package_type>container</package_type><owner_id>1226384</owner_id><owner>sagikazarmark</owner><repo>docker-sftpgo-with-plugins</repo><package>sftpgo-with-plugins</package><date>2024-10-09</date><size>162.6 MB</size><versions>1</versions><tagged>1</tagged><downloads>23.4k</downloads><downloads_month>16</downloads_month><downloads_week>4</downloads_week><downloads_day>0</downloads_day><raw_size>162690242</raw_size><raw_versions>1</raw_versions><raw_tagged>1</raw_tagged><raw_downloads>23402</raw_downloads><raw_downloads_month>16</raw_downloads_month><raw_downloads_week>4</raw_downloads_week><raw_downloads_day>0</raw_downloads_day><version><id>102416222</id><name>sha256:d24b255741384193133eab732e3275828a6ca6a1430995946da73b84ac7ee518</name><date>2024-10-09</date><newest>true</newest><latest>true</latest><size>162.6 MB</size><downloads>329</downloads><downloads_month>16</downloads_month><downloads_week>4</downloads_week><downloads_day>0</downloads_day><raw_size>162690242</raw_size><raw_downloads>329</raw_downloads><raw_downloads_month>16</raw_downloads_month><raw_downloads_week>4</raw_downloads_week><raw_downloads_day>0</raw_downloads_day><tags>v2.3.3-slim-1687008825</tags><tags>v2.3.3-slim</tags></version></bkg>
