<?xml version="1.0" encoding="UTF-8"?><bkg><owner_type>orgs</owner_type><package_type>container</package_type><owner_id>154642624</owner_id><owner>bobadojo</owner><repo>stores-server</repo><package>stores-server</package><date>2024-10-17</date><size>23.3 MB</size><versions>47</versions><tagged>40</tagged><downloads>939</downloads><downloads_month>196</downloads_month><downloads_week>61</downloads_week><downloads_day>0</downloads_day><raw_size>23383947</raw_size><raw_versions>47</raw_versions><raw_tagged>40</raw_tagged><raw_downloads>939</raw_downloads><raw_downloads_month>196</raw_downloads_month><raw_downloads_week>61</raw_downloads_week><raw_downloads_day>0</raw_downloads_day><version><id>262968473</id><name>sha256:94570f0527abf102b073658216f0837c6df6932ab8bbfe56f68391ac23784cea</name><date>2024-10-17</date><newest>false</newest><latest>false</latest><size>2.5 kB</size><downloads>0</downloads><downloads_month>0</downloads_month><downloads_week>0</downloads_week><downloads_day>0</downloads_day><raw_size>2560</raw_size><raw_downloads>0</raw_downloads><raw_downloads_month>0</raw_downloads_month><raw_downloads_week>0</raw_downloads_week><raw_downloads_day>0</raw_downloads_day><tags>nullnull[]</tags></version><version><id>262968474</id><name>sha256:9b56191d00d486c256ca148fbafbfc90eaf5d132498b40b7449b44c47693357e</name><date>2024-10-17</date><newest>false</newest><latest>false</latest><size>11.6 MB</size><downloads>0</downloads><downloads_month>0</downloads_month><downloads_week>0</downloads_week><downloads_day>0</downloads_day><raw_size>11661406</raw_size><raw_downloads>0</raw_downloads><raw_downloads_month>0</raw_downloads_month><raw_downloads_week>0</raw_downloads_week><raw_downloads_day>0</raw_downloads_day><tags>nullnull[]</tags></version><version><id>262968476</id><name>sha256:8b8ad87428d71c160500865b6628472e81c93544e6ecd1e62ffcd0d260e6e9c8</name><date>2024-10-17</date><newest>false</newest><latest>false</latest><size>11.7 MB</size><downloads>0</downloads><downloads_month>0</downloads_month><downloads_week>0</downloads_week><downloads_day>0</downloads_day><raw_size>11720038</raw_size><raw_downloads>0</raw_downloads><raw_downloads_month>0</raw_downloads_month><raw_downloads_week>0</raw_downloads_week><raw_downloads_day>0</raw_downloads_day><tags>nullnull[]</tags></version><version><id>262968477</id><name>sha256:b5e8fb8dfe26e4bd44e9ab45e7b1386d90db1f53bb381a01e6e429104fe6287a</name><date>2024-10-17</date><newest>false</newest><latest>false</latest><size>2.5 kB</size><downloads>0</downloads><downloads_month>0</downloads_month><downloads_week>0</downloads_week><downloads_day>0</downloads_day><raw_size>2560</raw_size><raw_downloads>0</raw_downloads><raw_downloads_month>0</raw_downloads_month><raw_downloads_week>0</raw_downloads_week><raw_downloads_day>0</raw_downloads_day><tags>nullnull[]</tags></version><version><id>262968478</id><name>sha256:9c82a465b3020c4e4d5f185bf7b8783a370b3752014f2d1fb6309217aac15dc4</name><date>2024-10-17</date><newest>false</newest><latest>false</latest><size>23.3 MB</size><downloads>0</downloads><downloads_month>0</downloads_month><downloads_week>0</downloads_week><downloads_day>0</downloads_day><raw_size>23382296</raw_size><raw_downloads>0</raw_downloads><raw_downloads_month>0</raw_downloads_month><raw_downloads_week>0</raw_downloads_week><raw_downloads_day>0</raw_downloads_day><tags>nullnull[]</tags></version><version><id>263184222</id><name>sha256:aedffcc3b5d5c560b891c9e2807fae38d6134d99d46928e649664ef672bde3ac</name><date>2024-10-17</date><newest>false</newest><latest>false</latest><size>11.6 MB</size><downloads>0</downloads><downloads_month>0</downloads_month><downloads_week>0</downloads_week><downloads_day>0</downloads_day><raw_size>11661398</raw_size><raw_downloads>0</raw_downloads><raw_downloads_month>0</raw_downloads_month><raw_downloads_week>0</raw_downloads_week><raw_downloads_day>0</raw_downloads_day><tags>nullnull[]</tags></version><version><id>263184228</id><name>sha256:b00ec354db91bf18f6f24b2bb687977c025a92fefe7dce5d12b208ed68ba2d3a</name><date>2024-10-17</date><newest>false</newest><latest>false</latest><size>2.5 kB</size><downloads>0</downloads><downloads_month>0</downloads_month><downloads_week>0</downloads_week><downloads_day>0</downloads_day><raw_size>2562</raw_size><raw_downloads>0</raw_downloads><raw_downloads_month>0</raw_downloads_month><raw_downloads_week>0</raw_downloads_week><raw_downloads_day>0</raw_downloads_day><tags>nullnull[]</tags></version><version><id>263184234</id><name>sha256:367fcf0927aaf1c3eebfa13adcf993ad69607a59a76da3cdbcae770d6eac495f</name><date>2024-10-17</date><newest>false</newest><latest>false</latest><size>11.7 MB</size><downloads>0</downloads><downloads_month>0</downloads_month><downloads_week>0</downloads_week><downloads_day>0</downloads_day><raw_size>11720043</raw_size><raw_downloads>0</raw_downloads><raw_downloads_month>0</raw_downloads_month><raw_downloads_week>0</raw_downloads_week><raw_downloads_day>0</raw_downloads_day><tags>nullnull[]</tags></version><version><id>263184238</id><name>sha256:8e138150e9b9f6217f33a3659b5429be8b2459c988e4b615f92bc12fcce1fa72</name><date>2024-10-17</date><newest>false</newest><latest>false</latest><size>2.5 kB</size><downloads>0</downloads><downloads_month>0</downloads_month><downloads_week>0</downloads_week><downloads_day>0</downloads_day><raw_size>2562</raw_size><raw_downloads>0</raw_downloads><raw_downloads_month>0</raw_downloads_month><raw_downloads_week>0</raw_downloads_week><raw_downloads_day>0</raw_downloads_day><tags>nullnull[]</tags></version><version><id>263796510</id><name>sha256:b52e54a77b8b6746e1fc81e041f0693cfbcd11ed4f4b40cfee34eca74998aa7a</name><date>2024-10-17</date><newest>false</newest><latest>false</latest><size>2.5 kB</size><downloads>0</downloads><downloads_month>0</downloads_month><downloads_week>0</downloads_week><downloads_day>0</downloads_day><raw_size>2562</raw_size><raw_downloads>0</raw_downloads><raw_downloads_month>0</raw_downloads_month><raw_downloads_week>0</raw_downloads_week><raw_downloads_day>0</raw_downloads_day><tags>nullnull[]</tags></version><version><id>264497575</id><name>sha256:0a5971ed8fb1724b235192b4d2866c86eb2f3349370baca2db6b8134948edfa9</name><date>2024-10-17</date><newest>false</newest><latest>false</latest><size>2.5 kB</size><downloads>0</downloads><downloads_month>0</downloads_month><downloads_week>0</downloads_week><downloads_day>0</downloads_day><raw_size>2562</raw_size><raw_downloads>0</raw_downloads><raw_downloads_month>0</raw_downloads_month><raw_downloads_week>0</raw_downloads_week><raw_downloads_day>0</raw_downloads_day><tags>nullnull[]</tags></version><version><id>264497577</id><name>sha256:e1e8b49815aa0f5a2114bb2026473f5d11d3b7e71c1cffe0075017766e20ff87</name><date>2024-10-17</date><newest>false</newest><latest>false</latest><size>11.6 MB</size><downloads>0</downloads><downloads_month>0</downloads_month><downloads_week>0</downloads_week><downloads_day>0</downloads_day><raw_size>11661410</raw_size><raw_downloads>0</raw_downloads><raw_downloads_month>0</raw_downloads_month><raw_downloads_week>0</raw_downloads_week><raw_downloads_day>0</raw_downloads_day><tags>nullnull[]</tags></version><version><id>264497578</id><name>sha256:e374a1da01171c108e804da96eb39a83579bc650898ba2b1cfa1a7ec3d469704</name><date>2024-10-17</date><newest>false</newest><latest>false</latest><size>11.7 MB</size><downloads>0</downloads><downloads_month>0</downloads_month><downloads_week>0</downloads_week><downloads_day>0</downloads_day><raw_size>11720032</raw_size><raw_downloads>0</raw_downloads><raw_downloads_month>0</raw_downloads_month><raw_downloads_week>0</raw_downloads_week><raw_downloads_day>0</raw_downloads_day><tags>nullnull[]</tags></version><version><id>264497580</id><name>sha256:47d4b37a183de589a847a61860d5653198f1ca350bfbeb14c366431883ca8fa8</name><date>2024-10-17</date><newest>false</newest><latest>false</latest><size>2.5 kB</size><downloads>0</downloads><downloads_month>0</downloads_month><downloads_week>0</downloads_week><downloads_day>0</downloads_day><raw_size>2562</raw_size><raw_downloads>0</raw_downloads><raw_downloads_month>0</raw_downloads_month><raw_downloads_week>0</raw_downloads_week><raw_downloads_day>0</raw_downloads_day><tags>nullnull[]</tags></version><version><id>265157114</id><name>sha256:fe522c0dc2a63104c0d2ed3948333cd4ffbac85452cbbe8fc550d23a62d77c90</name><date>2024-10-17</date><newest>false</newest><latest>false</latest><size>11.7 MB</size><downloads>0</downloads><downloads_month>0</downloads_month><downloads_week>0</downloads_week><downloads_day>0</downloads_day><raw_size>11720043</raw_size><raw_downloads>0</raw_downloads><raw_downloads_month>0</raw_downloads_month><raw_downloads_week>0</raw_downloads_week><raw_downloads_day>0</raw_downloads_day><tags>nullnull[]</tags></version><version><id>265157117</id><name>sha256:92b1a5971166ac905e8eab9d2147108ab18e731bf77d99193aa9be36f050f445</name><date>2024-10-17</date><newest>false</newest><latest>false</latest><size>2.5 kB</size><downloads>0</downloads><downloads_month>0</downloads_month><downloads_week>0</downloads_week><downloads_day>0</downloads_day><raw_size>2562</raw_size><raw_downloads>0</raw_downloads><raw_downloads_month>0</raw_downloads_month><raw_downloads_week>0</raw_downloads_week><raw_downloads_day>0</raw_downloads_day><tags>nullnull[]</tags></version><version><id>266307810</id><name>sha256:6c0c525537da5fb0aa77cb5b7052989e5ffc5979e3d0df9915d09b59f8357e42</name><date>2024-10-17</date><newest>false</newest><latest>false</latest><size>11.6 MB</size><downloads>0</downloads><downloads_month>0</downloads_month><downloads_week>0</downloads_week><downloads_day>0</downloads_day><raw_size>11661411</raw_size><raw_downloads>0</raw_downloads><raw_downloads_month>0</raw_downloads_month><raw_downloads_week>0</raw_downloads_week><raw_downloads_day>0</raw_downloads_day><tags>nullnull[]</tags></version><version><id>266307812</id><name>sha256:a63f2cbc522d9dfb34a89a4e81501f39e9eeed14b64f5ceccde9d753f45d627d</name><date>2024-10-17</date><newest>false</newest><latest>false</latest><size>11.7 MB</size><downloads>0</downloads><downloads_month>0</downloads_month><downloads_week>0</downloads_week><downloads_day>0</downloads_day><raw_size>11720045</raw_size><raw_downloads>0</raw_downloads><raw_downloads_month>0</raw_downloads_month><raw_downloads_week>0</raw_downloads_week><raw_downloads_day>0</raw_downloads_day><tags>nullnull[]</tags></version><version><id>266307814</id><name>sha256:62b7129a0b41132ce712d203d62c321fcfbe2e876988dfe29b3d1166c88e8fc2</name><date>2024-10-17</date><newest>false</newest><latest>false</latest><size>2.5 kB</size><downloads>0</downloads><downloads_month>0</downloads_month><downloads_week>0</downloads_week><downloads_day>0</downloads_day><raw_size>2562</raw_size><raw_downloads>0</raw_downloads><raw_downloads_month>0</raw_downloads_month><raw_downloads_week>0</raw_downloads_week><raw_downloads_day>0</raw_downloads_day><tags>nullnull[]</tags></version><version><id>267932087</id><name>sha256:f2973089c075001ae4de31a05ae9bff33438b5854fe916bced32584a032e00d9</name><date>2024-10-17</date><newest>false</newest><latest>false</latest><size>11.6 MB</size><downloads>7</downloads><downloads_month>7</downloads_month><downloads_week>3</downloads_week><downloads_day>0</downloads_day><raw_size>11661406</raw_size><raw_downloads>7</raw_downloads><raw_downloads_month>7</raw_downloads_month><raw_downloads_week>3</raw_downloads_week><raw_downloads_day>0</raw_downloads_day><tags>nullnull[]</tags></version><version><id>267932090</id><name>sha256:ccd1b00bc2e6c7a73576f414ce41fed4ca0cd36aafd353f826a5f1621e7cffba</name><date>2024-10-17</date><newest>false</newest><latest>false</latest><size>11.7 MB</size><downloads>12</downloads><downloads_month>12</downloads_month><downloads_week>3</downloads_week><downloads_day>0</downloads_day><raw_size>11720032</raw_size><raw_downloads>12</raw_downloads><raw_downloads_month>12</raw_downloads_month><raw_downloads_week>3</raw_downloads_week><raw_downloads_day>0</raw_downloads_day><tags></tags></version><version><id>267932094</id><name>sha256:a2ec2a255504793c84a86ef03a22d96f82af502b62e7d77c1528f34e5be582f3</name><date>2024-10-17</date><newest>false</newest><latest>false</latest><size>2.5 kB</size><downloads>7</downloads><downloads_month>7</downloads_month><downloads_week>3</downloads_week><downloads_day>0</downloads_day><raw_size>2562</raw_size><raw_downloads>7</raw_downloads><raw_downloads_month>7</raw_downloads_month><raw_downloads_week>3</raw_downloads_week><raw_downloads_day>0</raw_downloads_day><tags>nullnull[]</tags></version><version><id>267932096</id><name>sha256:7e04bb82a88fb4d6376ca8ae90975b91fd6d825f77c03639a5a8584f86fb7717</name><date>2024-10-17</date><newest>false</newest><latest>false</latest><size>23.3 MB</size><downloads>28</downloads><downloads_month>28</downloads_month><downloads_week>8</downloads_week><downloads_day>0</downloads_day><raw_size>23382294</raw_size><raw_downloads>28</raw_downloads><raw_downloads_month>28</raw_downloads_month><raw_downloads_week>8</raw_downloads_week><raw_downloads_day>0</raw_downloads_day><tags></tags></version><version><id>268608668</id><name>sha256:b6a4c9b5f804dbc7192c97632d15331478fe600b10689df5508b7b49e936101f</name><date>2024-10-17</date><newest>false</newest><latest>false</latest><size>2.5 kB</size><downloads>4</downloads><downloads_month>4</downloads_month><downloads_week>4</downloads_week><downloads_day>0</downloads_day><raw_size>2562</raw_size><raw_downloads>4</raw_downloads><raw_downloads_month>4</raw_downloads_month><raw_downloads_week>4</raw_downloads_week><raw_downloads_day>0</raw_downloads_day><tags>nullnull[]</tags></version><version><id>268608674</id><name>sha256:0168df6ea0a212f01ff2b29ab1bcfb4746900540f58028e90b728848bfd15466</name><date>2024-10-17</date><newest>false</newest><latest>false</latest><size>11.7 MB</size><downloads>7</downloads><downloads_month>7</downloads_month><downloads_week>3</downloads_week><downloads_day>0</downloads_day><raw_size>11720045</raw_size><raw_downloads>7</raw_downloads><raw_downloads_month>7</raw_downloads_month><raw_downloads_week>3</raw_downloads_week><raw_downloads_day>0</raw_downloads_day><tags>nullnull[]</tags></version><version><id>268608680</id><name>sha256:e6866c4a48b6a97e4299269b716db6123d9900d002fa4c1bb837a1b418d2f9d7</name><date>2024-10-17</date><newest>false</newest><latest>false</latest><size>11.6 MB</size><downloads>13</downloads><downloads_month>13</downloads_month><downloads_week>4</downloads_week><downloads_day>0</downloads_day><raw_size>11661411</raw_size><raw_downloads>13</raw_downloads><raw_downloads_month>13</raw_downloads_month><raw_downloads_week>4</raw_downloads_week><raw_downloads_day>0</raw_downloads_day><tags></tags></version><version><id>268608682</id><name>sha256:5f87e3d79b3a6b130e8f48b8c64a59b7bd0fe4aefdf6674c12374c6f080d8061</name><date>2024-10-17</date><newest>false</newest><latest>false</latest><size>2.5 kB</size><downloads>3</downloads><downloads_month>3</downloads_month><downloads_week>3</downloads_week><downloads_day>2</downloads_day><raw_size>2562</raw_size><raw_downloads>3</raw_downloads><raw_downloads_month>3</raw_downloads_month><raw_downloads_week>3</raw_downloads_week><raw_downloads_day>2</raw_downloads_day><tags>nullnull[]</tags></version><version><id>268608687</id><name>sha256:d1613164d37934ce511edbab9487a5380bfa2b12fc617e3819b61f56672683e9</name><date>2024-10-17</date><newest>false</newest><latest>false</latest><size>23.3 MB</size><downloads>26</downloads><downloads_month>26</downloads_month><downloads_week>8</downloads_week><downloads_day>0</downloads_day><raw_size>23382315</raw_size><raw_downloads>26</raw_downloads><raw_downloads_month>26</raw_downloads_month><raw_downloads_week>8</raw_downloads_week><raw_downloads_day>0</raw_downloads_day><tags></tags></version><version><id>269280291</id><name>sha256:888e03ad70ee48c6a9fdca6197bc04d00743e53660c23586b6a8c7e8fd3c3299</name><date>2024-10-17</date><newest>false</newest><latest>false</latest><size>2.3 kB</size><downloads>-1</downloads><downloads_month>-1</downloads_month><downloads_week>-1</downloads_week><downloads_day>-1</downloads_day><raw_size>2395</raw_size><raw_downloads>-1</raw_downloads><raw_downloads_month>-1</raw_downloads_month><raw_downloads_week>-1</raw_downloads_week><raw_downloads_day>-1</raw_downloads_day><tags></tags></version><version><id>269839077</id><name>sha256:c115953e6b2995661f5ef1779110e356e3d7da0c53aa32d9210f3e5b4d06b0a9</name><date>2024-10-17</date><newest>false</newest><latest>false</latest><size>2.5 kB</size><downloads>3</downloads><downloads_month>3</downloads_month><downloads_week>3</downloads_week><downloads_day>2</downloads_day><raw_size>2562</raw_size><raw_downloads>3</raw_downloads><raw_downloads_month>3</raw_downloads_month><raw_downloads_week>3</raw_downloads_week><raw_downloads_day>2</raw_downloads_day><tags>nullnull[]</tags></version><version><id>269839080</id><name>sha256:8f3fe470e251d601967887462854ccb4b213298d93b6c6a028e6fc12e1bed3e2</name><date>2024-10-17</date><newest>false</newest><latest>false</latest><size>23.3 MB</size><downloads>28</downloads><downloads_month>28</downloads_month><downloads_week>8</downloads_week><downloads_day>0</downloads_day><raw_size>23383910</raw_size><raw_downloads>28</raw_downloads><raw_downloads_month>28</raw_downloads_month><raw_downloads_week>8</raw_downloads_week><raw_downloads_day>0</raw_downloads_day><tags></tags></version><version><id>270038951</id><name>sha256:834c3f637990d0798f77071430fec26486ce6d119d93e9fcaa66df2df7e418fe</name><date>2024-10-17</date><newest>false</newest><latest>false</latest><size>11.7 MB</size><downloads>4</downloads><downloads_month>4</downloads_month><downloads_week>4</downloads_week><downloads_day>0</downloads_day><raw_size>11720753</raw_size><raw_downloads>4</raw_downloads><raw_downloads_month>4</raw_downloads_month><raw_downloads_week>4</raw_downloads_week><raw_downloads_day>0</raw_downloads_day><tags>nullnull[]</tags></version><version><id>270038955</id><name>sha256:bb8866cc6e95c7ef71ec693a17a6c621793d8cf5a85eafe8e4bc79cb41286ad1</name><date>2024-10-17</date><newest>false</newest><latest>false</latest><size>2.5 kB</size><downloads>15</downloads><downloads_month>15</downloads_month><downloads_week>5</downloads_week><downloads_day>0</downloads_day><raw_size>2562</raw_size><raw_downloads>15</raw_downloads><raw_downloads_month>15</raw_downloads_month><raw_downloads_week>5</raw_downloads_week><raw_downloads_day>0</raw_downloads_day><tags></tags></version><version><id>270038958</id><name>sha256:6b5846627aa587050ab8936fa797c8e2ad4a41dac20bff95d1e365ec9a58b0a8</name><date>2024-10-17</date><newest>false</newest><latest>false</latest><size>23.3 MB</size><downloads>28</downloads><downloads_month>28</downloads_month><downloads_week>8</downloads_week><downloads_day>0</downloads_day><raw_size>23383926</raw_size><raw_downloads>28</raw_downloads><raw_downloads_month>28</raw_downloads_month><raw_downloads_week>8</raw_downloads_week><raw_downloads_day>0</raw_downloads_day><tags></tags></version><version><id>270268431</id><name>sha256:e93510c1bbffb0c49888fec66cb9766fcc694d35f1071be0ae8d86710f160748</name><date>2024-10-17</date><newest>false</newest><latest>false</latest><size>11.6 MB</size><downloads>15</downloads><downloads_month>15</downloads_month><downloads_week>5</downloads_week><downloads_day>0</downloads_day><raw_size>11662325</raw_size><raw_downloads>15</raw_downloads><raw_downloads_month>15</raw_downloads_month><raw_downloads_week>5</raw_downloads_week><raw_downloads_day>0</raw_downloads_day><tags></tags></version><version><id>270268435</id><name>sha256:fc4dce96e8669d0f1689deae2038838e8b552bfa269449eed610b45ba27be125</name><date>2024-10-17</date><newest>false</newest><latest>false</latest><size>11.7 MB</size><downloads>-1</downloads><downloads_month>-1</downloads_month><downloads_week>-1</downloads_week><downloads_day>-1</downloads_day><raw_size>11718769</raw_size><raw_downloads>-1</raw_downloads><raw_downloads_month>-1</raw_downloads_month><raw_downloads_week>-1</raw_downloads_week><raw_downloads_day>-1</raw_downloads_day><tags></tags></version><version><id>270268437</id><name>sha256:d09f5a58a0997d48d45d610dd7ac379d4c91b333c7f65b50011a87b0495b335d</name><date>2024-10-17</date><newest>false</newest><latest>false</latest><size>2.5 kB</size><downloads>15</downloads><downloads_month>15</downloads_month><downloads_week>5</downloads_week><downloads_day>0</downloads_day><raw_size>2562</raw_size><raw_downloads>15</raw_downloads><raw_downloads_month>15</raw_downloads_month><raw_downloads_week>5</raw_downloads_week><raw_downloads_day>0</raw_downloads_day><tags></tags></version><version><id>270945025</id><name>sha256:994a81b1158c707516f8bb1d66a8b4b14b22265797c0533b314199d6543f8c85</name><date>2024-10-17</date><newest>false</newest><latest>false</latest><size>11.7 MB</size><downloads>0</downloads><downloads_month>0</downloads_month><downloads_week>0</downloads_week><downloads_day>0</downloads_day><raw_size>11720747</raw_size><raw_downloads>0</raw_downloads><raw_downloads_month>0</raw_downloads_month><raw_downloads_week>0</raw_downloads_week><raw_downloads_day>0</raw_downloads_day><tags>nullnull[]</tags></version><version><id>270945026</id><name>sha256:7afb9ac470978329d2749818d00c127cbf956e1806ede35ea4326f4d3347b8db</name><date>2024-10-17</date><newest>false</newest><latest>false</latest><size>2.3 kB</size><downloads>-1</downloads><downloads_month>-1</downloads_month><downloads_week>-1</downloads_week><downloads_day>-1</downloads_day><raw_size>2395</raw_size><raw_downloads>-1</raw_downloads><raw_downloads_month>-1</raw_downloads_month><raw_downloads_week>-1</raw_downloads_week><raw_downloads_day>-1</raw_downloads_day><tags></tags></version><version><id>270945032</id><name>sha256:561f09c7100873da04fd0c6370cc63d138cbafabe7d2a2cc9150b79871aa8961</name><date>2024-10-17</date><newest>false</newest><latest>false</latest><size>23.3 MB</size><downloads>8</downloads><downloads_month>8</downloads_month><downloads_week>8</downloads_week><downloads_day>0</downloads_day><raw_size>23383935</raw_size><raw_downloads>8</raw_downloads><raw_downloads_month>8</raw_downloads_month><raw_downloads_week>8</raw_downloads_week><raw_downloads_day>0</raw_downloads_day><tags>nullnull[]</tags></version><version><id>271665405</id><name>sha256:8da2dfbd0bd8b8e6b6390fefc941460ec4b450a1ec3243190f6afb1542e88392</name><date>2024-10-17</date><newest>false</newest><latest>false</latest><size>2.5 kB</size><downloads>4</downloads><downloads_month>4</downloads_month><downloads_week>4</downloads_week><downloads_day>0</downloads_day><raw_size>2562</raw_size><raw_downloads>4</raw_downloads><raw_downloads_month>4</raw_downloads_month><raw_downloads_week>4</raw_downloads_week><raw_downloads_day>0</raw_downloads_day><tags>nullnull[]</tags></version><version><id>271665407</id><name>sha256:9f68cc190b33cb563b40717c9e6e63ebdad76a635b96c7452354904dae6a1484</name><date>2024-10-17</date><newest>false</newest><latest>false</latest><size>2.5 kB</size><downloads>7</downloads><downloads_month>7</downloads_month><downloads_week>3</downloads_week><downloads_day>0</downloads_day><raw_size>2562</raw_size><raw_downloads>7</raw_downloads><raw_downloads_month>7</raw_downloads_month><raw_downloads_week>3</raw_downloads_week><raw_downloads_day>0</raw_downloads_day><tags>nullnull[]</tags></version><version><id>271665410</id><name>sha256:d133a4a8bb6381e614f1051e37172d663b45d62fed6ce1c9a68b7f0853dc5683</name><date>2024-10-17</date><newest>false</newest><latest>false</latest><size>23.3 MB</size><downloads>10</downloads><downloads_month>10</downloads_month><downloads_week>10</downloads_week><downloads_day>0</downloads_day><raw_size>23383937</raw_size><raw_downloads>10</raw_downloads><raw_downloads_month>10</raw_downloads_month><raw_downloads_week>10</raw_downloads_week><raw_downloads_day>0</raw_downloads_day><tags>nullnull[]</tags></version><version><id>272361215</id><name>sha256:6865893ababd992c75400c413328470b9b073e36e6b94abddeecf820dcdc588c</name><date>2024-10-17</date><newest>false</newest><latest>false</latest><size>23.3 MB</size><downloads>20</downloads><downloads_month>20</downloads_month><downloads_week>4</downloads_week><downloads_day>0</downloads_day><raw_size>23383927</raw_size><raw_downloads>20</raw_downloads><raw_downloads_month>20</raw_downloads_month><raw_downloads_week>4</raw_downloads_week><raw_downloads_day>0</raw_downloads_day><tags></tags></version><version><id>273039297</id><name>sha256:34824e4d9a49db1d758734add0d16e015851b6c835ad318e4a073e94d8ba268f</name><date>2024-10-17</date><newest>false</newest><latest>false</latest><size>2.5 kB</size><downloads>17</downloads><downloads_month>14</downloads_month><downloads_week>5</downloads_week><downloads_day>0</downloads_day><raw_size>2562</raw_size><raw_downloads>17</raw_downloads><raw_downloads_month>14</raw_downloads_month><raw_downloads_week>5</raw_downloads_week><raw_downloads_day>0</raw_downloads_day><tags></tags></version><version><id>273039299</id><name>sha256:cdd4e5a80966168447c69ae534b3512714dc87dd58df49ac7c6d4f409de2adaf</name><date>2024-10-17</date><newest>false</newest><latest>false</latest><size>2.5 kB</size><downloads>17</downloads><downloads_month>14</downloads_month><downloads_week>5</downloads_week><downloads_day>0</downloads_day><raw_size>2562</raw_size><raw_downloads>17</raw_downloads><raw_downloads_month>14</raw_downloads_month><raw_downloads_week>5</raw_downloads_week><raw_downloads_day>0</raw_downloads_day><tags></tags></version><version><id>273039303</id><name>sha256:8391f656d0c7b64254633132801a71efb452188179c4ee1eaf446250a2f561dd</name><date>2024-10-17</date><newest>true</newest><latest>true</latest><size>23.3 MB</size><downloads>-1</downloads><downloads_month>-1</downloads_month><downloads_week>-1</downloads_week><downloads_day>-1</downloads_day><raw_size>23383947</raw_size><raw_downloads>-1</raw_downloads><raw_downloads_month>-1</raw_downloads_month><raw_downloads_week>-1</raw_downloads_week><raw_downloads_day>-1</raw_downloads_day><tags>nightly</tags><tags>latest</tags><tags>main</tags></version></bkg>
