<?xml version="1.0" encoding="UTF-8"?><xml><owner_type>orgs</owner_type><package_type>container</package_type><owner_id>33221035</owner_id><owner>nix-community</owner><repo>docker-nixpkgs</repo><package>docker-nixpkgs%2Fcaddy</package><date>2024-12-12</date><size>28.1 MB</size><versions>2</versions><tagged>0</tagged><downloads>452</downloads><downloads_month>0</downloads_month><downloads_week>0</downloads_week><downloads_day>0</downloads_day><raw_size>28149908</raw_size><raw_versions>2</raw_versions><raw_tagged>0</raw_tagged><raw_downloads>452</raw_downloads><raw_downloads_month>0</raw_downloads_month><raw_downloads_week>0</raw_downloads_week><raw_downloads_day>0</raw_downloads_day><version><id>254277514</id><name>sha256:6996e278bdf33837a17766e8a9486d336bd22440e92a4c38f8549b931afe3195</name><date>2024-12-12</date><newest>false</newest><latest>false</latest><size>28 MB</size><downloads>0</downloads><downloads_month>0</downloads_month><downloads_week>0</downloads_week><downloads_day>0</downloads_day><raw_size>28002276</raw_size><raw_downloads>0</raw_downloads><raw_downloads_month>0</raw_downloads_month><raw_downloads_week>0</raw_downloads_week><raw_downloads_day>0</raw_downloads_day></version><version><id>289863374</id><name>sha256:2c65bdc465b67f7faa3d31eab6552ec7dfb3014f0e7c1456c401e821a8c276a8</name><date>2024-12-12</date><newest>true</newest><latest>false</latest><size>28.1 MB</size><downloads>0</downloads><downloads_month>0</downloads_month><downloads_week>0</downloads_week><downloads_day>0</downloads_day><raw_size>28149908</raw_size><raw_downloads>0</raw_downloads><raw_downloads_month>0</raw_downloads_month><raw_downloads_week>0</raw_downloads_week><raw_downloads_day>0</raw_downloads_day></version></xml>
