{"owner_type":"users","package_type":"container","owner_id":864213,"owner":"bayandin","repo":"homebrew-tap","package":"tap%2Fneon-extension","date":"2024-11-06","size":"313.4 kB","versions":"4","tagged":"3","downloads":"4.6k","downloads_month":"-1","downloads_week":"-1","downloads_day":"-1","raw_size":313491,"raw_versions":4,"raw_tagged":3,"raw_downloads":4673,"raw_downloads_month":-1,"raw_downloads_week":-1,"raw_downloads_day":-1,"version":[{"id":241115935,"name":"sha256:aef2afbf1deb34eb8dea464c80653d0650721f6e435aac2a980aef13cdd81c35","date":"2024-11-06","newest":false,"latest":false,"size":"-1","downloads":"-1","downloads_month":"-1","downloads_week":"-1","downloads_day":"-1","raw_size":-1,"raw_downloads":-1,"raw_downloads_month":-1,"raw_downloads_week":-1,"raw_downloads_day":-1,"tags":[]},{"id":248013402,"name":"sha256:30f86696fb25f1f78e2a430a5d292dfac304d6f679589f624e788cb493222b3a","date":"2024-11-06","newest":false,"latest":false,"size":"230.7 kB","downloads":"1","downloads_month":"0","downloads_week":"0","downloads_day":"0","raw_size":230771,"raw_downloads":1,"raw_downloads_month":0,"raw_downloads_week":0,"raw_downloads_day":0,"tags":["6136"]},{"id":267199332,"name":"sha256:e329e780ce1fdf99f1624494667f621fc7f3438591801a500c0ed289253cef20","date":"2024-11-06","newest":false,"latest":false,"size":"-1","downloads":"3","downloads_month":"0","downloads_week":"0","downloads_day":"0","raw_size":-1,"raw_downloads":3,"raw_downloads_month":0,"raw_downloads_week":0,"raw_downloads_day":0,"tags":["6548"]},{"id":275736665,"name":"sha256:8d31c0ecf47b0b1dbd341a16fdecfa6c5daa35eec9c0c03fcbc391fbdedd9731","date":"2024-11-06","newest":true,"latest":true,"size":"313.4 kB","downloads":"0","downloads_month":"0","downloads_week":"0","downloads_day":"0","raw_size":313491,"raw_downloads":0,"raw_downloads_month":0,"raw_downloads_week":0,"raw_downloads_day":0,"tags":["6616"]}]}
