{"owner_type":"orgs","package_type":"container","owner_id":76400755,"owner":"truecharts","repo":"containers","package":"n8n","date":"2024-10-06","size":"153.9 MB","versions":"3","tagged":"1","downloads":"34.6k","downloads_month":"7","downloads_week":"0","downloads_day":"0","raw_size":153960632,"raw_versions":3,"raw_tagged":1,"raw_downloads":34604,"raw_downloads_month":7,"raw_downloads_week":0,"raw_downloads_day":0,"version":[{"id":107874811,"name":"sha256:550badea7488bb41b11afe1aacd7463a9e6b5dcdc83b0b174938de1930c22062","date":"2024-10-06","newest":true,"latest":false,"size":"-1","downloads":"2","downloads_month":"0","downloads_week":"0","downloads_day":"0","raw_size":-1,"raw_downloads":2,"raw_downloads_month":0,"raw_downloads_week":0,"raw_downloads_day":0,"tags":[""]},{"id":88203732,"name":"sha256:6e62be81fcb3c3de7994bbb02e73f83b12844d79ab73e763ba4990d15584a482","date":"2024-10-06","newest":false,"latest":false,"size":"10.6 kB","downloads":"3","downloads_month":"3","downloads_week":"0","downloads_day":"0","raw_size":10641,"raw_downloads":3,"raw_downloads_month":3,"raw_downloads_week":0,"raw_downloads_day":0,"tags":[""]},{"id":88661543,"name":"sha256:ebabb297c818840335576d49cebe4443b7e8d84f25108c50d0a8863aba3e9db0","date":"2024-10-06","newest":false,"latest":true,"size":"153.9 MB","downloads":"602","downloads_month":"4","downloads_week":"0","downloads_day":"0","raw_size":153960632,"raw_downloads":602,"raw_downloads_month":4,"raw_downloads_week":0,"raw_downloads_day":0,"tags":["build20230426191307","0.226.0","v0.226.0","latest"]}]}
