{"owner_type":"users","package_type":"container","owner_id":7122237,"owner":"maslow","repo":"laf","package":"laf-runtime-controller","date":"2024-11-08","size":"26.4 MB","versions":"6","tagged":"0","downloads":"468","downloads_month":"-1","downloads_week":"-1","downloads_day":"-1","raw_size":26486513,"raw_versions":6,"raw_tagged":0,"raw_downloads":468,"raw_downloads_month":-1,"raw_downloads_week":-1,"raw_downloads_day":-1,"version":[{"id":47790103,"name":"sha256:7019a207d64c946756370726e2a0725c64282043ddce41f6387f935d62431781","date":"2024-11-08","newest":false,"latest":false,"size":"83.1 MB","downloads":"4","downloads_month":"0","downloads_week":"0","downloads_day":"0","raw_size":83137800,"raw_downloads":4,"raw_downloads_month":0,"raw_downloads_week":0,"raw_downloads_day":0,"tags":[]},{"id":48115529,"name":"sha256:48093a8d6e39c3219aba72a667700a9e08f3e93c489ed4366945010839525f0e","date":"2024-11-08","newest":false,"latest":false,"size":"83.1 MB","downloads":"4","downloads_month":"4","downloads_week":"0","downloads_day":"0","raw_size":83137775,"raw_downloads":4,"raw_downloads_month":4,"raw_downloads_week":0,"raw_downloads_day":0,"tags":[]},{"id":48690467,"name":"sha256:9d0bbad0614cd0b3b1d05a807a568aafefc5f630ae1ea33593ef3daa74b3304d","date":"2024-11-08","newest":false,"latest":false,"size":"26.4 MB","downloads":"4","downloads_month":"4","downloads_week":"0","downloads_day":"0","raw_size":26486500,"raw_downloads":4,"raw_downloads_month":4,"raw_downloads_week":0,"raw_downloads_day":0,"tags":[]},{"id":48722585,"name":"sha256:07a4b782bb4c387ee3ef5cb4084ff6130bf4f4df6b492021555209717caa195b","date":"2024-11-08","newest":false,"latest":false,"size":"26.4 MB","downloads":"4","downloads_month":"4","downloads_week":"0","downloads_day":"0","raw_size":26486513,"raw_downloads":4,"raw_downloads_month":4,"raw_downloads_week":0,"raw_downloads_day":0,"tags":[]},{"id":48732113,"name":"sha256:99435d743f629c007e1f01ef8a701de4e74fbb81a5fea817c3397f0242013aac","date":"2024-11-08","newest":false,"latest":false,"size":"-1","downloads":"8","downloads_month":"8","downloads_week":"0","downloads_day":"0","raw_size":-1,"raw_downloads":8,"raw_downloads_month":8,"raw_downloads_week":0,"raw_downloads_day":0,"tags":[]},{"id":48736564,"name":"sha256:5c21b6bedde1fec78d5ef18ff76b33a3d05d8450506db7d2373213be0cb27802","date":"2024-11-08","newest":true,"latest":false,"size":"26.4 MB","downloads":"4","downloads_month":"4","downloads_week":"0","downloads_day":"0","raw_size":26486513,"raw_downloads":4,"raw_downloads_month":4,"raw_downloads_week":0,"raw_downloads_day":0,"tags":[]}]}
