<?xml version="1.0" encoding="UTF-8"?><bkg><owner_type>users</owner_type><package_type>container</package_type><owner_id>7122237</owner_id><owner>maslow</owner><repo>laf</repo><package>laf-runtime-controller</package><date>2024-10-09</date><size>24.6 MB</size><versions>5</versions><tagged>0</tagged><downloads>424</downloads><downloads_month>19</downloads_month><downloads_week>18</downloads_week><downloads_day>0</downloads_day><raw_size>24650839</raw_size><raw_versions>5</raw_versions><raw_tagged>0</raw_tagged><raw_downloads>424</raw_downloads><raw_downloads_month>19</raw_downloads_month><raw_downloads_week>18</raw_downloads_week><raw_downloads_day>0</raw_downloads_day><version><id>47790106</id><name>sha256:fcf8ea50be925fa03fa508b388f955350a4a81580c50355dc42b92082d7e59f6</name><date>2024-10-09</date><newest>false</newest><latest>false</latest><size>164.4 MB</size><downloads>6</downloads><downloads_month>6</downloads_month><downloads_week>6</downloads_week><downloads_day>0</downloads_day><raw_size>164429097</raw_size><raw_downloads>6</raw_downloads><raw_downloads_month>6</raw_downloads_month><raw_downloads_week>6</raw_downloads_week><raw_downloads_day>0</raw_downloads_day><tags></tags></version><version><id>48722585</id><name>sha256:07a4b782bb4c387ee3ef5cb4084ff6130bf4f4df6b492021555209717caa195b</name><date>2024-10-09</date><newest>false</newest><latest>false</latest><size>26.4 MB</size><downloads>3</downloads><downloads_month>3</downloads_month><downloads_week>3</downloads_week><downloads_day>0</downloads_day><raw_size>26486513</raw_size><raw_downloads>3</raw_downloads><raw_downloads_month>3</raw_downloads_month><raw_downloads_week>3</raw_downloads_week><raw_downloads_day>0</raw_downloads_day><tags></tags></version><version><id>48736564</id><name>sha256:5c21b6bedde1fec78d5ef18ff76b33a3d05d8450506db7d2373213be0cb27802</name><date>2024-10-09</date><newest>false</newest><latest>false</latest><size>26.4 MB</size><downloads>3</downloads><downloads_month>3</downloads_month><downloads_week>3</downloads_week><downloads_day>0</downloads_day><raw_size>26486513</raw_size><raw_downloads>3</raw_downloads><raw_downloads_month>3</raw_downloads_month><raw_downloads_week>3</raw_downloads_week><raw_downloads_day>0</raw_downloads_day><tags></tags></version><version><id>48736566</id><name>sha256:4dde7719dd9c6f7d625b155c493b9c3f3f4a097aea98974bbcf59a5a98a6b255</name><date>2024-10-09</date><newest>false</newest><latest>false</latest><size>24.6 MB</size><downloads>3</downloads><downloads_month>3</downloads_month><downloads_week>3</downloads_week><downloads_day>0</downloads_day><raw_size>24643689</raw_size><raw_downloads>3</raw_downloads><raw_downloads_month>3</raw_downloads_month><raw_downloads_week>3</raw_downloads_week><raw_downloads_day>0</raw_downloads_day><tags></tags></version><version><id>54872795</id><name>sha256:7679b7197e72da4f4e494d3e9169dc5c13b3348f2e280280d69f789d669a89fa</name><date>2024-10-09</date><newest>true</newest><latest>false</latest><size>24.6 MB</size><downloads>6</downloads><downloads_month>4</downloads_month><downloads_week>3</downloads_week><downloads_day>0</downloads_day><raw_size>24650839</raw_size><raw_downloads>6</raw_downloads><raw_downloads_month>4</raw_downloads_month><raw_downloads_week>3</raw_downloads_week><raw_downloads_day>0</raw_downloads_day><tags></tags></version></bkg>
