{"owner_type":"users","package_type":"container","owner_id":5567,"owner":"rafaelgaspar","repo":"docker-homebridge","package":"homebridge","date":"2024-09-16","size":"994.3 MB","versions":"42","tagged":"42","downloads":"2.4k","downloads_month":"1.6k","downloads_week":"457","downloads_day":"48","raw_size":994349002,"raw_versions":42,"raw_tagged":42,"raw_downloads":2431,"raw_downloads_month":1693,"raw_downloads_week":457,"raw_downloads_day":48,"version":[{"id":-1,"name":"latest","date":"2024-09-16","newest":true,"latest":true,"size":"994.3 MB","downloads":"2.4k","downloads_month":"1.6k","downloads_week":"457","downloads_day":"48","raw_size":994349002,"raw_downloads":2431,"raw_downloads_month":1693,"raw_downloads_week":457,"raw_downloads_day":48,"tags":[""]}]}
